{"response":{"count":3824,"items":[{"inner_type":"wall_wallpost","donut":{"is_donut":false},"check_sign":true,"comments":{"can_post":1,"can_view":1,"count":0,"groups_can_post":true},"marked_as_ads":0,"hash":"ZigpcxDObCbLbqsjmA","type":"post","push_subscription":{"is_subscribed":false},"attachments":[{"type":"video","video":{"response_type":"full","access_key":"b29a703c7d6ecbaa1d","can_like":1,"can_repost":1,"can_subscribe":1,"can_add":1,"comments":0,"date":1743918130,"description":"","duration":51,"image":[{"url":"https:\/\/i.mycdn.me\/getVideoPreview?id=8105399683832&idx=8&type=39&tkn=ZTS3u9VsxJhkXtgjMAyVQD9bjZ0&fn=vid_s","width":130,"height":96,"with_padding":1},{"url":"https:\/\/i.mycdn.me\/getVideoPreview?id=8105399683832&idx=8&type=39&tkn=ZTS3u9VsxJhkXtgjMAyVQD9bjZ0&fn=vid_m","width":160,"height":120,"with_padding":1},{"url":"https:\/\/i.mycdn.me\/getVideoPreview?id=8105399683832&idx=8&type=39&tkn=ZTS3u9VsxJhkXtgjMAyVQD9bjZ0&fn=vid_l","width":320,"height":240,"with_padding":1},{"url":"https:\/\/i.mycdn.me\/getVideoPreview?id=8105399683832&idx=8&type=39&tkn=ZTS3u9VsxJhkXtgjMAyVQD9bjZ0&fn=vid_x","width":800,"height":450,"with_padding":1},{"url":"https:\/\/i.mycdn.me\/getVideoPreview?id=8105399683832&idx=8&type=39&tkn=ZTS3u9VsxJhkXtgjMAyVQD9bjZ0&fn=vid_w","width":1280,"height":700},{"url":"https:\/\/i.mycdn.me\/getVideoPreview?id=8105399683832&idx=8&type=39&tkn=ZTS3u9VsxJhkXtgjMAyVQD9bjZ0&fn=vid_t","width":320,"height":175},{"url":"https:\/\/i.mycdn.me\/getVideoPreview?id=8105399683832&idx=8&type=39&tkn=ZTS3u9VsxJhkXtgjMAyVQD9bjZ0&fn=vid_u","width":720,"height":394}],"first_frame":[{"url":"https:\/\/i.mycdn.me\/getVideoPreview?id=8105399683832&idx=0&type=39&tkn=4DOfTnT0aCcTIoBMhSGx64UPn48&fn=vid_f","width":720,"height":405},{"url":"https:\/\/i.mycdn.me\/getVideoPreview?id=8105399683832&idx=0&type=39&tkn=4DOfTnT0aCcTIoBMhSGx64UPn48&fn=vid_md","width":480,"height":270},{"url":"https:\/\/i.mycdn.me\/getVideoPreview?id=8105399683832&idx=0&type=39&tkn=4DOfTnT0aCcTIoBMhSGx64UPn48&fn=vid_d","width":240,"height":135},{"url":"https:\/\/i.mycdn.me\/getVideoPreview?id=8105399683832&idx=0&type=39&tkn=4DOfTnT0aCcTIoBMhSGx64UPn48&fn=vid_sm","width":128,"height":72},{"url":"https:\/\/i.mycdn.me\/getVideoPreview?id=8105399683832&idx=0&type=39&tkn=4DOfTnT0aCcTIoBMhSGx64UPn48&fn=vid_w","width":1280,"height":720},{"url":"https:\/\/i.mycdn.me\/getVideoPreview?id=8105399683832&idx=0&type=39&tkn=4DOfTnT0aCcTIoBMhSGx64UPn48&fn=vid_h","width":960,"height":540},{"url":"https:\/\/i.mycdn.me\/getVideoPreview?id=8105399683832&idx=0&type=39&tkn=4DOfTnT0aCcTIoBMhSGx64UPn48&fn=vid_w","width":1280,"height":720}],"width":1280,"height":700,"id":456240418,"owner_id":-174700694,"title":"Video.Guru_20250406_093849107.mp4","track_code":"video_0abd3dfc1lqSknT0_VkoxNLdrLbgnIH1HCMoomV1pmzxaYetfWHheY-Tdfn-NiDE0tzzgtWqs8EsFxKaYQLHAJ1piIBMVtVOQFy8PzWW5w0U6A","type":"video","views":433,"local_views":433,"can_dislike":1,"should_stretch":false}}],"date":1743952871,"from_id":-174700694,"id":8695,"likes":{"can_like":1,"count":15,"user_likes":0,"can_publish":1,"repost_disabled":false},"reaction_set_id":"reactions","reactions":{"count":15,"items":[{"id":0,"count":15}]},"owner_id":-174700694,"post_source":{"platform":"iphone","type":"api"},"post_type":"post","reposts":{"count":1,"user_reposted":0},"text":"🤔 Как выбрать подходящую профессию? Как понять,чем ты захочешь заниматься каждый день, и что тебя действительно увлекает и развивает? \n✅ Надо попробовать себя!\n\nТакая возможность предоставилась школьникам МБУ «Школа №34» и МБУ «Школа имени С.П. Королёва», где амбассадоры ТСПК провели мастер- классы.\n\nВ ходе мастер-классов школьники погрузились в мир педагогики, ИТ, физической культуры и дошкольного воспитания. 🥰\n\n#ВЧД2025 \n#Профессионалы \n#СПО\n#Профессионалы63\n#85летСПО\n#ВсероссийскоеДвижениеПрофессионалы\n#ДействуйКакПрофессионал\n#ПрофессионалыСделаноВРоссии\n#Амбассадоры_Профессионалитета #Профессионалитетг #Первый_Педагогический \n#ТСПК_в_сердце\n#Тывхорошейкомпании","views":{"count":566}},{"inner_type":"wall_wallpost","donut":{"is_donut":false},"comments":{"can_post":1,"can_view":1,"count":1,"groups_can_post":true},"marked_as_ads":0,"hash":"JSN9cRX_lex4yVGspQ","type":"post","push_subscription":{"is_subscribed":false},"carousel_offset":0,"attachments":[{"type":"photo","photo":{"album_id":-7,"date":1743835403,"id":457273809,"owner_id":-174700694,"access_key":"070d6449d84fbe0e63","sizes":[{"height":56,"type":"s","width":75,"url":"https:\/\/sun9-35.userapi.com\/s\/v1\/ig2\/jvShQ_oRR6Ec6rSsYJIu9joB2UKKUXKcS2EtOUiDun3XC-VHyt0B0enhPjcJAeZzNf3iPlkBiD_E2e3YucyXXFhC.jpg?quality=95&as=32x24,48x36,72x54,108x81,160x120,240x180,360x270,480x360,540x405,640x480,720x540,1080x810,1280x960&from=bu&cs=75x56"},{"height":97,"type":"m","width":130,"url":"https:\/\/sun9-35.userapi.com\/s\/v1\/ig2\/jvShQ_oRR6Ec6rSsYJIu9joB2UKKUXKcS2EtOUiDun3XC-VHyt0B0enhPjcJAeZzNf3iPlkBiD_E2e3YucyXXFhC.jpg?quality=95&as=32x24,48x36,72x54,108x81,160x120,240x180,360x270,480x360,540x405,640x480,720x540,1080x810,1280x960&from=bu&cs=130x97"},{"height":453,"type":"x","width":604,"url":"https:\/\/sun9-35.userapi.com\/s\/v1\/ig2\/jvShQ_oRR6Ec6rSsYJIu9joB2UKKUXKcS2EtOUiDun3XC-VHyt0B0enhPjcJAeZzNf3iPlkBiD_E2e3YucyXXFhC.jpg?quality=95&as=32x24,48x36,72x54,108x81,160x120,240x180,360x270,480x360,540x405,640x480,720x540,1080x810,1280x960&from=bu&cs=604x453"},{"height":605,"type":"y","width":807,"url":"https:\/\/sun9-35.userapi.com\/s\/v1\/ig2\/jvShQ_oRR6Ec6rSsYJIu9joB2UKKUXKcS2EtOUiDun3XC-VHyt0B0enhPjcJAeZzNf3iPlkBiD_E2e3YucyXXFhC.jpg?quality=95&as=32x24,48x36,72x54,108x81,160x120,240x180,360x270,480x360,540x405,640x480,720x540,1080x810,1280x960&from=bu&cs=807x605"},{"height":960,"type":"z","width":1280,"url":"https:\/\/sun9-35.userapi.com\/s\/v1\/ig2\/jvShQ_oRR6Ec6rSsYJIu9joB2UKKUXKcS2EtOUiDun3XC-VHyt0B0enhPjcJAeZzNf3iPlkBiD_E2e3YucyXXFhC.jpg?quality=95&as=32x24,48x36,72x54,108x81,160x120,240x180,360x270,480x360,540x405,640x480,720x540,1080x810,1280x960&from=bu&cs=1280x960"},{"height":97,"type":"o","width":130,"url":"https:\/\/sun9-35.userapi.com\/s\/v1\/ig2\/jvShQ_oRR6Ec6rSsYJIu9joB2UKKUXKcS2EtOUiDun3XC-VHyt0B0enhPjcJAeZzNf3iPlkBiD_E2e3YucyXXFhC.jpg?quality=95&as=32x24,48x36,72x54,108x81,160x120,240x180,360x270,480x360,540x405,640x480,720x540,1080x810,1280x960&from=bu&cs=130x97"},{"height":150,"type":"p","width":200,"url":"https:\/\/sun9-35.userapi.com\/s\/v1\/ig2\/jvShQ_oRR6Ec6rSsYJIu9joB2UKKUXKcS2EtOUiDun3XC-VHyt0B0enhPjcJAeZzNf3iPlkBiD_E2e3YucyXXFhC.jpg?quality=95&as=32x24,48x36,72x54,108x81,160x120,240x180,360x270,480x360,540x405,640x480,720x540,1080x810,1280x960&from=bu&cs=200x150"},{"height":240,"type":"q","width":320,"url":"https:\/\/sun9-35.userapi.com\/s\/v1\/ig2\/jvShQ_oRR6Ec6rSsYJIu9joB2UKKUXKcS2EtOUiDun3XC-VHyt0B0enhPjcJAeZzNf3iPlkBiD_E2e3YucyXXFhC.jpg?quality=95&as=32x24,48x36,72x54,108x81,160x120,240x180,360x270,480x360,540x405,640x480,720x540,1080x810,1280x960&from=bu&cs=320x240"},{"height":382,"type":"r","width":510,"url":"https:\/\/sun9-35.userapi.com\/s\/v1\/ig2\/jvShQ_oRR6Ec6rSsYJIu9joB2UKKUXKcS2EtOUiDun3XC-VHyt0B0enhPjcJAeZzNf3iPlkBiD_E2e3YucyXXFhC.jpg?quality=95&as=32x24,48x36,72x54,108x81,160x120,240x180,360x270,480x360,540x405,640x480,720x540,1080x810,1280x960&from=bu&cs=510x382"}],"text":"","user_id":100,"web_view_token":"fe55946b5fc3b5fdcf","has_tags":false,"orig_photo":{"height":960,"type":"base","url":"https:\/\/sun9-35.userapi.com\/s\/v1\/ig2\/jvShQ_oRR6Ec6rSsYJIu9joB2UKKUXKcS2EtOUiDun3XC-VHyt0B0enhPjcJAeZzNf3iPlkBiD_E2e3YucyXXFhC.jpg?quality=95&as=32x24,48x36,72x54,108x81,160x120,240x180,360x270,480x360,540x405,640x480,720x540,1080x810,1280x960&from=bu","width":1280}}},{"type":"photo","photo":{"album_id":-7,"date":1743835403,"id":457273810,"owner_id":-174700694,"access_key":"b94dd15466776bbe14","sizes":[{"height":34,"type":"s","width":75,"url":"https:\/\/sun9-27.userapi.com\/s\/v1\/ig2\/zRl0f2koowy3pee13sSM0NcHH2zptQ9oihKI0RrSi1pzhFHRlMo2oHrO0NOsjPVjp0Z1hXYR0xPZdy_80pCcoHl3.jpg?quality=95&as=32x14,48x22,72x33,108x49,160x72,240x109,360x163,480x217,540x244,640x289,720x326,1080x489,1280x579&from=bu&cs=75x34"},{"height":59,"type":"m","width":130,"url":"https:\/\/sun9-27.userapi.com\/s\/v1\/ig2\/zRl0f2koowy3pee13sSM0NcHH2zptQ9oihKI0RrSi1pzhFHRlMo2oHrO0NOsjPVjp0Z1hXYR0xPZdy_80pCcoHl3.jpg?quality=95&as=32x14,48x22,72x33,108x49,160x72,240x109,360x163,480x217,540x244,640x289,720x326,1080x489,1280x579&from=bu&cs=130x59"},{"height":273,"type":"x","width":604,"url":"https:\/\/sun9-27.userapi.com\/s\/v1\/ig2\/zRl0f2koowy3pee13sSM0NcHH2zptQ9oihKI0RrSi1pzhFHRlMo2oHrO0NOsjPVjp0Z1hXYR0xPZdy_80pCcoHl3.jpg?quality=95&as=32x14,48x22,72x33,108x49,160x72,240x109,360x163,480x217,540x244,640x289,720x326,1080x489,1280x579&from=bu&cs=604x273"},{"height":365,"type":"y","width":807,"url":"https:\/\/sun9-27.userapi.com\/s\/v1\/ig2\/zRl0f2koowy3pee13sSM0NcHH2zptQ9oihKI0RrSi1pzhFHRlMo2oHrO0NOsjPVjp0Z1hXYR0xPZdy_80pCcoHl3.jpg?quality=95&as=32x14,48x22,72x33,108x49,160x72,240x109,360x163,480x217,540x244,640x289,720x326,1080x489,1280x579&from=bu&cs=807x365"},{"height":579,"type":"z","width":1280,"url":"https:\/\/sun9-27.userapi.com\/s\/v1\/ig2\/zRl0f2koowy3pee13sSM0NcHH2zptQ9oihKI0RrSi1pzhFHRlMo2oHrO0NOsjPVjp0Z1hXYR0xPZdy_80pCcoHl3.jpg?quality=95&as=32x14,48x22,72x33,108x49,160x72,240x109,360x163,480x217,540x244,640x289,720x326,1080x489,1280x579&from=bu&cs=1280x579"},{"height":87,"type":"o","width":130,"url":"https:\/\/sun9-27.userapi.com\/s\/v1\/ig2\/zRl0f2koowy3pee13sSM0NcHH2zptQ9oihKI0RrSi1pzhFHRlMo2oHrO0NOsjPVjp0Z1hXYR0xPZdy_80pCcoHl3.jpg?quality=95&as=32x14,48x22,72x33,108x49,160x72,240x109,360x163,480x217,540x244,640x289,720x326,1080x489,1280x579&from=bu&cs=130x87"},{"height":133,"type":"p","width":200,"url":"https:\/\/sun9-27.userapi.com\/s\/v1\/ig2\/zRl0f2koowy3pee13sSM0NcHH2zptQ9oihKI0RrSi1pzhFHRlMo2oHrO0NOsjPVjp0Z1hXYR0xPZdy_80pCcoHl3.jpg?quality=95&as=32x14,48x22,72x33,108x49,160x72,240x109,360x163,480x217,540x244,640x289,720x326,1080x489,1280x579&from=bu&cs=200x133"},{"height":213,"type":"q","width":320,"url":"https:\/\/sun9-27.userapi.com\/s\/v1\/ig2\/zRl0f2koowy3pee13sSM0NcHH2zptQ9oihKI0RrSi1pzhFHRlMo2oHrO0NOsjPVjp0Z1hXYR0xPZdy_80pCcoHl3.jpg?quality=95&as=32x14,48x22,72x33,108x49,160x72,240x109,360x163,480x217,540x244,640x289,720x326,1080x489,1280x579&from=bu&cs=320x213"},{"height":340,"type":"r","width":510,"url":"https:\/\/sun9-27.userapi.com\/s\/v1\/ig2\/zRl0f2koowy3pee13sSM0NcHH2zptQ9oihKI0RrSi1pzhFHRlMo2oHrO0NOsjPVjp0Z1hXYR0xPZdy_80pCcoHl3.jpg?quality=95&as=32x14,48x22,72x33,108x49,160x72,240x109,360x163,480x217,540x244,640x289,720x326,1080x489,1280x579&from=bu&cs=510x340"}],"text":"","user_id":100,"web_view_token":"9b84afc674e9db417c","has_tags":false,"orig_photo":{"height":579,"type":"base","url":"https:\/\/sun9-27.userapi.com\/s\/v1\/ig2\/zRl0f2koowy3pee13sSM0NcHH2zptQ9oihKI0RrSi1pzhFHRlMo2oHrO0NOsjPVjp0Z1hXYR0xPZdy_80pCcoHl3.jpg?quality=95&as=32x14,48x22,72x33,108x49,160x72,240x109,360x163,480x217,540x244,640x289,720x326,1080x489,1280x579&from=bu","width":1280}}},{"type":"photo","photo":{"album_id":-7,"date":1743835403,"id":457273811,"owner_id":-174700694,"access_key":"a2d0c201a5c87cf010","sizes":[{"height":75,"type":"s","width":56,"url":"https:\/\/sun9-14.userapi.com\/s\/v1\/ig2\/ZA857oJMt9Yr9Zy3Kgv1ew7O6AVgp2wxskh6WWjN8B97mlZPRDTpdGM9--NH8zVzveN5DssvzheIWhCozLbhU4kH.jpg?quality=95&as=32x43,48x64,72x96,108x144,160x213,240x320,360x480,480x640,540x720,640x853,720x960,960x1280&from=bu&cs=56x75"},{"height":130,"type":"m","width":97,"url":"https:\/\/sun9-14.userapi.com\/s\/v1\/ig2\/ZA857oJMt9Yr9Zy3Kgv1ew7O6AVgp2wxskh6WWjN8B97mlZPRDTpdGM9--NH8zVzveN5DssvzheIWhCozLbhU4kH.jpg?quality=95&as=32x43,48x64,72x96,108x144,160x213,240x320,360x480,480x640,540x720,640x853,720x960,960x1280&from=bu&cs=97x130"},{"height":604,"type":"x","width":453,"url":"https:\/\/sun9-14.userapi.com\/s\/v1\/ig2\/ZA857oJMt9Yr9Zy3Kgv1ew7O6AVgp2wxskh6WWjN8B97mlZPRDTpdGM9--NH8zVzveN5DssvzheIWhCozLbhU4kH.jpg?quality=95&as=32x43,48x64,72x96,108x144,160x213,240x320,360x480,480x640,540x720,640x853,720x960,960x1280&from=bu&cs=453x604"},{"height":807,"type":"y","width":605,"url":"https:\/\/sun9-14.userapi.com\/s\/v1\/ig2\/ZA857oJMt9Yr9Zy3Kgv1ew7O6AVgp2wxskh6WWjN8B97mlZPRDTpdGM9--NH8zVzveN5DssvzheIWhCozLbhU4kH.jpg?quality=95&as=32x43,48x64,72x96,108x144,160x213,240x320,360x480,480x640,540x720,640x853,720x960,960x1280&from=bu&cs=605x807"},{"height":1080,"type":"z","width":810,"url":"https:\/\/sun9-14.userapi.com\/s\/v1\/ig2\/ZA857oJMt9Yr9Zy3Kgv1ew7O6AVgp2wxskh6WWjN8B97mlZPRDTpdGM9--NH8zVzveN5DssvzheIWhCozLbhU4kH.jpg?quality=95&as=32x43,48x64,72x96,108x144,160x213,240x320,360x480,480x640,540x720,640x853,720x960,960x1280&from=bu&cs=810x1080"},{"height":1280,"type":"w","width":960,"url":"https:\/\/sun9-14.userapi.com\/s\/v1\/ig2\/ZA857oJMt9Yr9Zy3Kgv1ew7O6AVgp2wxskh6WWjN8B97mlZPRDTpdGM9--NH8zVzveN5DssvzheIWhCozLbhU4kH.jpg?quality=95&as=32x43,48x64,72x96,108x144,160x213,240x320,360x480,480x640,540x720,640x853,720x960,960x1280&from=bu&cs=960x1280"},{"height":173,"type":"o","width":130,"url":"https:\/\/sun9-14.userapi.com\/s\/v1\/ig2\/ZA857oJMt9Yr9Zy3Kgv1ew7O6AVgp2wxskh6WWjN8B97mlZPRDTpdGM9--NH8zVzveN5DssvzheIWhCozLbhU4kH.jpg?quality=95&as=32x43,48x64,72x96,108x144,160x213,240x320,360x480,480x640,540x720,640x853,720x960,960x1280&from=bu&cs=130x173"},{"height":267,"type":"p","width":200,"url":"https:\/\/sun9-14.userapi.com\/s\/v1\/ig2\/ZA857oJMt9Yr9Zy3Kgv1ew7O6AVgp2wxskh6WWjN8B97mlZPRDTpdGM9--NH8zVzveN5DssvzheIWhCozLbhU4kH.jpg?quality=95&as=32x43,48x64,72x96,108x144,160x213,240x320,360x480,480x640,540x720,640x853,720x960,960x1280&from=bu&cs=200x267"},{"height":427,"type":"q","width":320,"url":"https:\/\/sun9-14.userapi.com\/s\/v1\/ig2\/ZA857oJMt9Yr9Zy3Kgv1ew7O6AVgp2wxskh6WWjN8B97mlZPRDTpdGM9--NH8zVzveN5DssvzheIWhCozLbhU4kH.jpg?quality=95&as=32x43,48x64,72x96,108x144,160x213,240x320,360x480,480x640,540x720,640x853,720x960,960x1280&from=bu&cs=320x427"},{"height":680,"type":"r","width":510,"url":"https:\/\/sun9-14.userapi.com\/s\/v1\/ig2\/ZA857oJMt9Yr9Zy3Kgv1ew7O6AVgp2wxskh6WWjN8B97mlZPRDTpdGM9--NH8zVzveN5DssvzheIWhCozLbhU4kH.jpg?quality=95&as=32x43,48x64,72x96,108x144,160x213,240x320,360x480,480x640,540x720,640x853,720x960,960x1280&from=bu&cs=510x680"}],"text":"","user_id":100,"web_view_token":"898de8fb3fb4d395d6","has_tags":false,"orig_photo":{"height":1280,"type":"base","url":"https:\/\/sun9-14.userapi.com\/s\/v1\/ig2\/ZA857oJMt9Yr9Zy3Kgv1ew7O6AVgp2wxskh6WWjN8B97mlZPRDTpdGM9--NH8zVzveN5DssvzheIWhCozLbhU4kH.jpg?quality=95&as=32x43,48x64,72x96,108x144,160x213,240x320,360x480,480x640,540x720,640x853,720x960,960x1280&from=bu","width":960}}},{"type":"photo","photo":{"album_id":-7,"date":1743835403,"id":457273812,"owner_id":-174700694,"access_key":"67b084b966b11356bb","sizes":[{"height":56,"type":"s","width":75,"url":"https:\/\/sun9-63.userapi.com\/s\/v1\/ig2\/rtyILX1wpMohIaj5Mpwi5kHB0ju6uUcuZwbuPz1LNYnQ053feh1AiOKhxH_GJQ08quefPF00OV02bwPNZFhEpko7.jpg?quality=95&as=32x24,48x36,72x54,108x81,160x120,240x180,360x270,480x360,540x405,640x480,720x540,1080x810,1280x960&from=bu&cs=75x56"},{"height":97,"type":"m","width":130,"url":"https:\/\/sun9-63.userapi.com\/s\/v1\/ig2\/rtyILX1wpMohIaj5Mpwi5kHB0ju6uUcuZwbuPz1LNYnQ053feh1AiOKhxH_GJQ08quefPF00OV02bwPNZFhEpko7.jpg?quality=95&as=32x24,48x36,72x54,108x81,160x120,240x180,360x270,480x360,540x405,640x480,720x540,1080x810,1280x960&from=bu&cs=130x97"},{"height":453,"type":"x","width":604,"url":"https:\/\/sun9-63.userapi.com\/s\/v1\/ig2\/rtyILX1wpMohIaj5Mpwi5kHB0ju6uUcuZwbuPz1LNYnQ053feh1AiOKhxH_GJQ08quefPF00OV02bwPNZFhEpko7.jpg?quality=95&as=32x24,48x36,72x54,108x81,160x120,240x180,360x270,480x360,540x405,640x480,720x540,1080x810,1280x960&from=bu&cs=604x453"},{"height":605,"type":"y","width":807,"url":"https:\/\/sun9-63.userapi.com\/s\/v1\/ig2\/rtyILX1wpMohIaj5Mpwi5kHB0ju6uUcuZwbuPz1LNYnQ053feh1AiOKhxH_GJQ08quefPF00OV02bwPNZFhEpko7.jpg?quality=95&as=32x24,48x36,72x54,108x81,160x120,240x180,360x270,480x360,540x405,640x480,720x540,1080x810,1280x960&from=bu&cs=807x605"},{"height":960,"type":"z","width":1280,"url":"https:\/\/sun9-63.userapi.com\/s\/v1\/ig2\/rtyILX1wpMohIaj5Mpwi5kHB0ju6uUcuZwbuPz1LNYnQ053feh1AiOKhxH_GJQ08quefPF00OV02bwPNZFhEpko7.jpg?quality=95&as=32x24,48x36,72x54,108x81,160x120,240x180,360x270,480x360,540x405,640x480,720x540,1080x810,1280x960&from=bu&cs=1280x960"},{"height":97,"type":"o","width":130,"url":"https:\/\/sun9-63.userapi.com\/s\/v1\/ig2\/rtyILX1wpMohIaj5Mpwi5kHB0ju6uUcuZwbuPz1LNYnQ053feh1AiOKhxH_GJQ08quefPF00OV02bwPNZFhEpko7.jpg?quality=95&as=32x24,48x36,72x54,108x81,160x120,240x180,360x270,480x360,540x405,640x480,720x540,1080x810,1280x960&from=bu&cs=130x97"},{"height":150,"type":"p","width":200,"url":"https:\/\/sun9-63.userapi.com\/s\/v1\/ig2\/rtyILX1wpMohIaj5Mpwi5kHB0ju6uUcuZwbuPz1LNYnQ053feh1AiOKhxH_GJQ08quefPF00OV02bwPNZFhEpko7.jpg?quality=95&as=32x24,48x36,72x54,108x81,160x120,240x180,360x270,480x360,540x405,640x480,720x540,1080x810,1280x960&from=bu&cs=200x150"},{"height":240,"type":"q","width":320,"url":"https:\/\/sun9-63.userapi.com\/s\/v1\/ig2\/rtyILX1wpMohIaj5Mpwi5kHB0ju6uUcuZwbuPz1LNYnQ053feh1AiOKhxH_GJQ08quefPF00OV02bwPNZFhEpko7.jpg?quality=95&as=32x24,48x36,72x54,108x81,160x120,240x180,360x270,480x360,540x405,640x480,720x540,1080x810,1280x960&from=bu&cs=320x240"},{"height":382,"type":"r","width":510,"url":"https:\/\/sun9-63.userapi.com\/s\/v1\/ig2\/rtyILX1wpMohIaj5Mpwi5kHB0ju6uUcuZwbuPz1LNYnQ053feh1AiOKhxH_GJQ08quefPF00OV02bwPNZFhEpko7.jpg?quality=95&as=32x24,48x36,72x54,108x81,160x120,240x180,360x270,480x360,540x405,640x480,720x540,1080x810,1280x960&from=bu&cs=510x382"}],"text":"","user_id":100,"web_view_token":"b76259b0bf73f363af","has_tags":false,"orig_photo":{"height":960,"type":"base","url":"https:\/\/sun9-63.userapi.com\/s\/v1\/ig2\/rtyILX1wpMohIaj5Mpwi5kHB0ju6uUcuZwbuPz1LNYnQ053feh1AiOKhxH_GJQ08quefPF00OV02bwPNZFhEpko7.jpg?quality=95&as=32x24,48x36,72x54,108x81,160x120,240x180,360x270,480x360,540x405,640x480,720x540,1080x810,1280x960&from=bu","width":1280}}},{"type":"photo","photo":{"album_id":-7,"date":1743835403,"id":457273813,"owner_id":-174700694,"access_key":"b6e804a64a6af4e3f9","sizes":[{"height":56,"type":"s","width":75,"url":"https:\/\/sun9-80.userapi.com\/s\/v1\/ig2\/F8gFmK6Hh0kf7-VL2S8o-KI3krDqBLI_7XGrLwTPBJ_xIayT4svSbuBx-8zQrHRhX-Jgnt-fIpO0_-ZFCi-G8BD2.jpg?quality=95&as=32x24,48x36,72x54,108x81,160x120,240x180,360x270,480x360,540x405,640x480,720x540,1080x810,1280x960&from=bu&cs=75x56"},{"height":97,"type":"m","width":130,"url":"https:\/\/sun9-80.userapi.com\/s\/v1\/ig2\/F8gFmK6Hh0kf7-VL2S8o-KI3krDqBLI_7XGrLwTPBJ_xIayT4svSbuBx-8zQrHRhX-Jgnt-fIpO0_-ZFCi-G8BD2.jpg?quality=95&as=32x24,48x36,72x54,108x81,160x120,240x180,360x270,480x360,540x405,640x480,720x540,1080x810,1280x960&from=bu&cs=130x97"},{"height":453,"type":"x","width":604,"url":"https:\/\/sun9-80.userapi.com\/s\/v1\/ig2\/F8gFmK6Hh0kf7-VL2S8o-KI3krDqBLI_7XGrLwTPBJ_xIayT4svSbuBx-8zQrHRhX-Jgnt-fIpO0_-ZFCi-G8BD2.jpg?quality=95&as=32x24,48x36,72x54,108x81,160x120,240x180,360x270,480x360,540x405,640x480,720x540,1080x810,1280x960&from=bu&cs=604x453"},{"height":605,"type":"y","width":807,"url":"https:\/\/sun9-80.userapi.com\/s\/v1\/ig2\/F8gFmK6Hh0kf7-VL2S8o-KI3krDqBLI_7XGrLwTPBJ_xIayT4svSbuBx-8zQrHRhX-Jgnt-fIpO0_-ZFCi-G8BD2.jpg?quality=95&as=32x24,48x36,72x54,108x81,160x120,240x180,360x270,480x360,540x405,640x480,720x540,1080x810,1280x960&from=bu&cs=807x605"},{"height":960,"type":"z","width":1280,"url":"https:\/\/sun9-80.userapi.com\/s\/v1\/ig2\/F8gFmK6Hh0kf7-VL2S8o-KI3krDqBLI_7XGrLwTPBJ_xIayT4svSbuBx-8zQrHRhX-Jgnt-fIpO0_-ZFCi-G8BD2.jpg?quality=95&as=32x24,48x36,72x54,108x81,160x120,240x180,360x270,480x360,540x405,640x480,720x540,1080x810,1280x960&from=bu&cs=1280x960"},{"height":97,"type":"o","width":130,"url":"https:\/\/sun9-80.userapi.com\/s\/v1\/ig2\/F8gFmK6Hh0kf7-VL2S8o-KI3krDqBLI_7XGrLwTPBJ_xIayT4svSbuBx-8zQrHRhX-Jgnt-fIpO0_-ZFCi-G8BD2.jpg?quality=95&as=32x24,48x36,72x54,108x81,160x120,240x180,360x270,480x360,540x405,640x480,720x540,1080x810,1280x960&from=bu&cs=130x97"},{"height":150,"type":"p","width":200,"url":"https:\/\/sun9-80.userapi.com\/s\/v1\/ig2\/F8gFmK6Hh0kf7-VL2S8o-KI3krDqBLI_7XGrLwTPBJ_xIayT4svSbuBx-8zQrHRhX-Jgnt-fIpO0_-ZFCi-G8BD2.jpg?quality=95&as=32x24,48x36,72x54,108x81,160x120,240x180,360x270,480x360,540x405,640x480,720x540,1080x810,1280x960&from=bu&cs=200x150"},{"height":240,"type":"q","width":320,"url":"https:\/\/sun9-80.userapi.com\/s\/v1\/ig2\/F8gFmK6Hh0kf7-VL2S8o-KI3krDqBLI_7XGrLwTPBJ_xIayT4svSbuBx-8zQrHRhX-Jgnt-fIpO0_-ZFCi-G8BD2.jpg?quality=95&as=32x24,48x36,72x54,108x81,160x120,240x180,360x270,480x360,540x405,640x480,720x540,1080x810,1280x960&from=bu&cs=320x240"},{"height":382,"type":"r","width":510,"url":"https:\/\/sun9-80.userapi.com\/s\/v1\/ig2\/F8gFmK6Hh0kf7-VL2S8o-KI3krDqBLI_7XGrLwTPBJ_xIayT4svSbuBx-8zQrHRhX-Jgnt-fIpO0_-ZFCi-G8BD2.jpg?quality=95&as=32x24,48x36,72x54,108x81,160x120,240x180,360x270,480x360,540x405,640x480,720x540,1080x810,1280x960&from=bu&cs=510x382"}],"text":"","user_id":100,"web_view_token":"0026762b005b4e8783","has_tags":false,"orig_photo":{"height":960,"type":"base","url":"https:\/\/sun9-80.userapi.com\/s\/v1\/ig2\/F8gFmK6Hh0kf7-VL2S8o-KI3krDqBLI_7XGrLwTPBJ_xIayT4svSbuBx-8zQrHRhX-Jgnt-fIpO0_-ZFCi-G8BD2.jpg?quality=95&as=32x24,48x36,72x54,108x81,160x120,240x180,360x270,480x360,540x405,640x480,720x540,1080x810,1280x960&from=bu","width":1280}}},{"type":"photo","photo":{"album_id":-7,"date":1743835403,"id":457273814,"owner_id":-174700694,"access_key":"cf305d6fb6c8f57bb8","sizes":[{"height":75,"type":"s","width":56,"url":"https:\/\/sun9-71.userapi.com\/s\/v1\/ig2\/gn6HVs0ts8_HGObmZ0xrylH9XMhKg0lbIwUJkotXMiZJe5weKGNBK-z8_SS5Cz92_rgDwxCfKoGHS1dC4S0Uq46t.jpg?quality=95&as=32x43,48x64,72x96,108x144,160x213,240x320,360x480,480x640,540x720,640x853,720x960,960x1280&from=bu&cs=56x75"},{"height":130,"type":"m","width":97,"url":"https:\/\/sun9-71.userapi.com\/s\/v1\/ig2\/gn6HVs0ts8_HGObmZ0xrylH9XMhKg0lbIwUJkotXMiZJe5weKGNBK-z8_SS5Cz92_rgDwxCfKoGHS1dC4S0Uq46t.jpg?quality=95&as=32x43,48x64,72x96,108x144,160x213,240x320,360x480,480x640,540x720,640x853,720x960,960x1280&from=bu&cs=97x130"},{"height":604,"type":"x","width":453,"url":"https:\/\/sun9-71.userapi.com\/s\/v1\/ig2\/gn6HVs0ts8_HGObmZ0xrylH9XMhKg0lbIwUJkotXMiZJe5weKGNBK-z8_SS5Cz92_rgDwxCfKoGHS1dC4S0Uq46t.jpg?quality=95&as=32x43,48x64,72x96,108x144,160x213,240x320,360x480,480x640,540x720,640x853,720x960,960x1280&from=bu&cs=453x604"},{"height":807,"type":"y","width":605,"url":"https:\/\/sun9-71.userapi.com\/s\/v1\/ig2\/gn6HVs0ts8_HGObmZ0xrylH9XMhKg0lbIwUJkotXMiZJe5weKGNBK-z8_SS5Cz92_rgDwxCfKoGHS1dC4S0Uq46t.jpg?quality=95&as=32x43,48x64,72x96,108x144,160x213,240x320,360x480,480x640,540x720,640x853,720x960,960x1280&from=bu&cs=605x807"},{"height":1080,"type":"z","width":810,"url":"https:\/\/sun9-71.userapi.com\/s\/v1\/ig2\/gn6HVs0ts8_HGObmZ0xrylH9XMhKg0lbIwUJkotXMiZJe5weKGNBK-z8_SS5Cz92_rgDwxCfKoGHS1dC4S0Uq46t.jpg?quality=95&as=32x43,48x64,72x96,108x144,160x213,240x320,360x480,480x640,540x720,640x853,720x960,960x1280&from=bu&cs=810x1080"},{"height":1280,"type":"w","width":960,"url":"https:\/\/sun9-71.userapi.com\/s\/v1\/ig2\/gn6HVs0ts8_HGObmZ0xrylH9XMhKg0lbIwUJkotXMiZJe5weKGNBK-z8_SS5Cz92_rgDwxCfKoGHS1dC4S0Uq46t.jpg?quality=95&as=32x43,48x64,72x96,108x144,160x213,240x320,360x480,480x640,540x720,640x853,720x960,960x1280&from=bu&cs=960x1280"},{"height":173,"type":"o","width":130,"url":"https:\/\/sun9-71.userapi.com\/s\/v1\/ig2\/gn6HVs0ts8_HGObmZ0xrylH9XMhKg0lbIwUJkotXMiZJe5weKGNBK-z8_SS5Cz92_rgDwxCfKoGHS1dC4S0Uq46t.jpg?quality=95&as=32x43,48x64,72x96,108x144,160x213,240x320,360x480,480x640,540x720,640x853,720x960,960x1280&from=bu&cs=130x173"},{"height":267,"type":"p","width":200,"url":"https:\/\/sun9-71.userapi.com\/s\/v1\/ig2\/gn6HVs0ts8_HGObmZ0xrylH9XMhKg0lbIwUJkotXMiZJe5weKGNBK-z8_SS5Cz92_rgDwxCfKoGHS1dC4S0Uq46t.jpg?quality=95&as=32x43,48x64,72x96,108x144,160x213,240x320,360x480,480x640,540x720,640x853,720x960,960x1280&from=bu&cs=200x267"},{"height":427,"type":"q","width":320,"url":"https:\/\/sun9-71.userapi.com\/s\/v1\/ig2\/gn6HVs0ts8_HGObmZ0xrylH9XMhKg0lbIwUJkotXMiZJe5weKGNBK-z8_SS5Cz92_rgDwxCfKoGHS1dC4S0Uq46t.jpg?quality=95&as=32x43,48x64,72x96,108x144,160x213,240x320,360x480,480x640,540x720,640x853,720x960,960x1280&from=bu&cs=320x427"},{"height":680,"type":"r","width":510,"url":"https:\/\/sun9-71.userapi.com\/s\/v1\/ig2\/gn6HVs0ts8_HGObmZ0xrylH9XMhKg0lbIwUJkotXMiZJe5weKGNBK-z8_SS5Cz92_rgDwxCfKoGHS1dC4S0Uq46t.jpg?quality=95&as=32x43,48x64,72x96,108x144,160x213,240x320,360x480,480x640,540x720,640x853,720x960,960x1280&from=bu&cs=510x680"}],"text":"","user_id":100,"web_view_token":"3156ebe531fc550e91","has_tags":false,"orig_photo":{"height":1280,"type":"base","url":"https:\/\/sun9-71.userapi.com\/s\/v1\/ig2\/gn6HVs0ts8_HGObmZ0xrylH9XMhKg0lbIwUJkotXMiZJe5weKGNBK-z8_SS5Cz92_rgDwxCfKoGHS1dC4S0Uq46t.jpg?quality=95&as=32x43,48x64,72x96,108x144,160x213,240x320,360x480,480x640,540x720,640x853,720x960,960x1280&from=bu","width":960}}},{"type":"photo","photo":{"album_id":-7,"date":1743835403,"id":457273815,"owner_id":-174700694,"access_key":"94e2c72375d9bbcf33","sizes":[{"height":75,"type":"s","width":56,"url":"https:\/\/sun9-66.userapi.com\/s\/v1\/ig2\/c7HpZGpj_TZl2WgMV1hqcwWvOZcw8MHzGPqrnnmbdYtFFz4vHfsEU8o9BrvScdExq8PKSbLMLJ1_Ix4Ve-n0r0Hp.jpg?quality=95&as=32x43,48x64,72x96,108x144,160x213,240x320,360x480,480x640,540x720,640x853,720x960,960x1280&from=bu&cs=56x75"},{"height":130,"type":"m","width":97,"url":"https:\/\/sun9-66.userapi.com\/s\/v1\/ig2\/c7HpZGpj_TZl2WgMV1hqcwWvOZcw8MHzGPqrnnmbdYtFFz4vHfsEU8o9BrvScdExq8PKSbLMLJ1_Ix4Ve-n0r0Hp.jpg?quality=95&as=32x43,48x64,72x96,108x144,160x213,240x320,360x480,480x640,540x720,640x853,720x960,960x1280&from=bu&cs=97x130"},{"height":604,"type":"x","width":453,"url":"https:\/\/sun9-66.userapi.com\/s\/v1\/ig2\/c7HpZGpj_TZl2WgMV1hqcwWvOZcw8MHzGPqrnnmbdYtFFz4vHfsEU8o9BrvScdExq8PKSbLMLJ1_Ix4Ve-n0r0Hp.jpg?quality=95&as=32x43,48x64,72x96,108x144,160x213,240x320,360x480,480x640,540x720,640x853,720x960,960x1280&from=bu&cs=453x604"},{"height":807,"type":"y","width":605,"url":"https:\/\/sun9-66.userapi.com\/s\/v1\/ig2\/c7HpZGpj_TZl2WgMV1hqcwWvOZcw8MHzGPqrnnmbdYtFFz4vHfsEU8o9BrvScdExq8PKSbLMLJ1_Ix4Ve-n0r0Hp.jpg?quality=95&as=32x43,48x64,72x96,108x144,160x213,240x320,360x480,480x640,540x720,640x853,720x960,960x1280&from=bu&cs=605x807"},{"height":1080,"type":"z","width":810,"url":"https:\/\/sun9-66.userapi.com\/s\/v1\/ig2\/c7HpZGpj_TZl2WgMV1hqcwWvOZcw8MHzGPqrnnmbdYtFFz4vHfsEU8o9BrvScdExq8PKSbLMLJ1_Ix4Ve-n0r0Hp.jpg?quality=95&as=32x43,48x64,72x96,108x144,160x213,240x320,360x480,480x640,540x720,640x853,720x960,960x1280&from=bu&cs=810x1080"},{"height":1280,"type":"w","width":960,"url":"https:\/\/sun9-66.userapi.com\/s\/v1\/ig2\/c7HpZGpj_TZl2WgMV1hqcwWvOZcw8MHzGPqrnnmbdYtFFz4vHfsEU8o9BrvScdExq8PKSbLMLJ1_Ix4Ve-n0r0Hp.jpg?quality=95&as=32x43,48x64,72x96,108x144,160x213,240x320,360x480,480x640,540x720,640x853,720x960,960x1280&from=bu&cs=960x1280"},{"height":173,"type":"o","width":130,"url":"https:\/\/sun9-66.userapi.com\/s\/v1\/ig2\/c7HpZGpj_TZl2WgMV1hqcwWvOZcw8MHzGPqrnnmbdYtFFz4vHfsEU8o9BrvScdExq8PKSbLMLJ1_Ix4Ve-n0r0Hp.jpg?quality=95&as=32x43,48x64,72x96,108x144,160x213,240x320,360x480,480x640,540x720,640x853,720x960,960x1280&from=bu&cs=130x173"},{"height":267,"type":"p","width":200,"url":"https:\/\/sun9-66.userapi.com\/s\/v1\/ig2\/c7HpZGpj_TZl2WgMV1hqcwWvOZcw8MHzGPqrnnmbdYtFFz4vHfsEU8o9BrvScdExq8PKSbLMLJ1_Ix4Ve-n0r0Hp.jpg?quality=95&as=32x43,48x64,72x96,108x144,160x213,240x320,360x480,480x640,540x720,640x853,720x960,960x1280&from=bu&cs=200x267"},{"height":427,"type":"q","width":320,"url":"https:\/\/sun9-66.userapi.com\/s\/v1\/ig2\/c7HpZGpj_TZl2WgMV1hqcwWvOZcw8MHzGPqrnnmbdYtFFz4vHfsEU8o9BrvScdExq8PKSbLMLJ1_Ix4Ve-n0r0Hp.jpg?quality=95&as=32x43,48x64,72x96,108x144,160x213,240x320,360x480,480x640,540x720,640x853,720x960,960x1280&from=bu&cs=320x427"},{"height":680,"type":"r","width":510,"url":"https:\/\/sun9-66.userapi.com\/s\/v1\/ig2\/c7HpZGpj_TZl2WgMV1hqcwWvOZcw8MHzGPqrnnmbdYtFFz4vHfsEU8o9BrvScdExq8PKSbLMLJ1_Ix4Ve-n0r0Hp.jpg?quality=95&as=32x43,48x64,72x96,108x144,160x213,240x320,360x480,480x640,540x720,640x853,720x960,960x1280&from=bu&cs=510x680"}],"text":"","user_id":100,"web_view_token":"0f68952c6eefa9fcca","has_tags":false,"orig_photo":{"height":1280,"type":"base","url":"https:\/\/sun9-66.userapi.com\/s\/v1\/ig2\/c7HpZGpj_TZl2WgMV1hqcwWvOZcw8MHzGPqrnnmbdYtFFz4vHfsEU8o9BrvScdExq8PKSbLMLJ1_Ix4Ve-n0r0Hp.jpg?quality=95&as=32x43,48x64,72x96,108x144,160x213,240x320,360x480,480x640,540x720,640x853,720x960,960x1280&from=bu","width":960}}},{"type":"photo","photo":{"album_id":-7,"date":1743835403,"id":457273816,"owner_id":-174700694,"access_key":"1a6b8310e9d5ba3bb8","sizes":[{"height":75,"type":"s","width":56,"url":"https:\/\/sun9-14.userapi.com\/s\/v1\/ig2\/sg5f3VL3kts5ezDglVsL2HQQChPzdwBkK2NclTkyCSMMGkZ_djSqnCyJZPzZIFKULNwsqE4G_g4LIi-m9esK3Cy8.jpg?quality=95&as=32x43,48x64,72x96,108x144,160x213,240x320,360x480,480x640,540x720,640x853,720x960,960x1280&from=bu&cs=56x75"},{"height":130,"type":"m","width":97,"url":"https:\/\/sun9-14.userapi.com\/s\/v1\/ig2\/sg5f3VL3kts5ezDglVsL2HQQChPzdwBkK2NclTkyCSMMGkZ_djSqnCyJZPzZIFKULNwsqE4G_g4LIi-m9esK3Cy8.jpg?quality=95&as=32x43,48x64,72x96,108x144,160x213,240x320,360x480,480x640,540x720,640x853,720x960,960x1280&from=bu&cs=97x130"},{"height":604,"type":"x","width":453,"url":"https:\/\/sun9-14.userapi.com\/s\/v1\/ig2\/sg5f3VL3kts5ezDglVsL2HQQChPzdwBkK2NclTkyCSMMGkZ_djSqnCyJZPzZIFKULNwsqE4G_g4LIi-m9esK3Cy8.jpg?quality=95&as=32x43,48x64,72x96,108x144,160x213,240x320,360x480,480x640,540x720,640x853,720x960,960x1280&from=bu&cs=453x604"},{"height":807,"type":"y","width":605,"url":"https:\/\/sun9-14.userapi.com\/s\/v1\/ig2\/sg5f3VL3kts5ezDglVsL2HQQChPzdwBkK2NclTkyCSMMGkZ_djSqnCyJZPzZIFKULNwsqE4G_g4LIi-m9esK3Cy8.jpg?quality=95&as=32x43,48x64,72x96,108x144,160x213,240x320,360x480,480x640,540x720,640x853,720x960,960x1280&from=bu&cs=605x807"},{"height":1080,"type":"z","width":810,"url":"https:\/\/sun9-14.userapi.com\/s\/v1\/ig2\/sg5f3VL3kts5ezDglVsL2HQQChPzdwBkK2NclTkyCSMMGkZ_djSqnCyJZPzZIFKULNwsqE4G_g4LIi-m9esK3Cy8.jpg?quality=95&as=32x43,48x64,72x96,108x144,160x213,240x320,360x480,480x640,540x720,640x853,720x960,960x1280&from=bu&cs=810x1080"},{"height":1280,"type":"w","width":960,"url":"https:\/\/sun9-14.userapi.com\/s\/v1\/ig2\/sg5f3VL3kts5ezDglVsL2HQQChPzdwBkK2NclTkyCSMMGkZ_djSqnCyJZPzZIFKULNwsqE4G_g4LIi-m9esK3Cy8.jpg?quality=95&as=32x43,48x64,72x96,108x144,160x213,240x320,360x480,480x640,540x720,640x853,720x960,960x1280&from=bu&cs=960x1280"},{"height":173,"type":"o","width":130,"url":"https:\/\/sun9-14.userapi.com\/s\/v1\/ig2\/sg5f3VL3kts5ezDglVsL2HQQChPzdwBkK2NclTkyCSMMGkZ_djSqnCyJZPzZIFKULNwsqE4G_g4LIi-m9esK3Cy8.jpg?quality=95&as=32x43,48x64,72x96,108x144,160x213,240x320,360x480,480x640,540x720,640x853,720x960,960x1280&from=bu&cs=130x173"},{"height":267,"type":"p","width":200,"url":"https:\/\/sun9-14.userapi.com\/s\/v1\/ig2\/sg5f3VL3kts5ezDglVsL2HQQChPzdwBkK2NclTkyCSMMGkZ_djSqnCyJZPzZIFKULNwsqE4G_g4LIi-m9esK3Cy8.jpg?quality=95&as=32x43,48x64,72x96,108x144,160x213,240x320,360x480,480x640,540x720,640x853,720x960,960x1280&from=bu&cs=200x267"},{"height":427,"type":"q","width":320,"url":"https:\/\/sun9-14.userapi.com\/s\/v1\/ig2\/sg5f3VL3kts5ezDglVsL2HQQChPzdwBkK2NclTkyCSMMGkZ_djSqnCyJZPzZIFKULNwsqE4G_g4LIi-m9esK3Cy8.jpg?quality=95&as=32x43,48x64,72x96,108x144,160x213,240x320,360x480,480x640,540x720,640x853,720x960,960x1280&from=bu&cs=320x427"},{"height":680,"type":"r","width":510,"url":"https:\/\/sun9-14.userapi.com\/s\/v1\/ig2\/sg5f3VL3kts5ezDglVsL2HQQChPzdwBkK2NclTkyCSMMGkZ_djSqnCyJZPzZIFKULNwsqE4G_g4LIi-m9esK3Cy8.jpg?quality=95&as=32x43,48x64,72x96,108x144,160x213,240x320,360x480,480x640,540x720,640x853,720x960,960x1280&from=bu&cs=510x680"}],"text":"","user_id":100,"web_view_token":"96153f11bccf0357eb","has_tags":false,"orig_photo":{"height":1280,"type":"base","url":"https:\/\/sun9-14.userapi.com\/s\/v1\/ig2\/sg5f3VL3kts5ezDglVsL2HQQChPzdwBkK2NclTkyCSMMGkZ_djSqnCyJZPzZIFKULNwsqE4G_g4LIi-m9esK3Cy8.jpg?quality=95&as=32x43,48x64,72x96,108x144,160x213,240x320,360x480,480x640,540x720,640x853,720x960,960x1280&from=bu","width":960}}},{"type":"photo","photo":{"album_id":-7,"date":1743835403,"id":457273817,"owner_id":-174700694,"access_key":"c6fdc747600d9f18b0","sizes":[{"height":56,"type":"s","width":75,"url":"https:\/\/sun9-27.userapi.com\/s\/v1\/ig2\/PQTYi54nnZUU2HKekzpgw0WPjGyS_MJF5UDFTTgJXD5M02hkGQghPshhDMz1fU4AxR6h8B6KOFfrVyM2saaC50T9.jpg?quality=95&as=32x24,48x36,72x54,108x81,160x120,240x180,360x270,480x360,540x405,640x480,720x540,1080x810,1280x960&from=bu&cs=75x56"},{"height":97,"type":"m","width":130,"url":"https:\/\/sun9-27.userapi.com\/s\/v1\/ig2\/PQTYi54nnZUU2HKekzpgw0WPjGyS_MJF5UDFTTgJXD5M02hkGQghPshhDMz1fU4AxR6h8B6KOFfrVyM2saaC50T9.jpg?quality=95&as=32x24,48x36,72x54,108x81,160x120,240x180,360x270,480x360,540x405,640x480,720x540,1080x810,1280x960&from=bu&cs=130x97"},{"height":453,"type":"x","width":604,"url":"https:\/\/sun9-27.userapi.com\/s\/v1\/ig2\/PQTYi54nnZUU2HKekzpgw0WPjGyS_MJF5UDFTTgJXD5M02hkGQghPshhDMz1fU4AxR6h8B6KOFfrVyM2saaC50T9.jpg?quality=95&as=32x24,48x36,72x54,108x81,160x120,240x180,360x270,480x360,540x405,640x480,720x540,1080x810,1280x960&from=bu&cs=604x453"},{"height":605,"type":"y","width":807,"url":"https:\/\/sun9-27.userapi.com\/s\/v1\/ig2\/PQTYi54nnZUU2HKekzpgw0WPjGyS_MJF5UDFTTgJXD5M02hkGQghPshhDMz1fU4AxR6h8B6KOFfrVyM2saaC50T9.jpg?quality=95&as=32x24,48x36,72x54,108x81,160x120,240x180,360x270,480x360,540x405,640x480,720x540,1080x810,1280x960&from=bu&cs=807x605"},{"height":960,"type":"z","width":1280,"url":"https:\/\/sun9-27.userapi.com\/s\/v1\/ig2\/PQTYi54nnZUU2HKekzpgw0WPjGyS_MJF5UDFTTgJXD5M02hkGQghPshhDMz1fU4AxR6h8B6KOFfrVyM2saaC50T9.jpg?quality=95&as=32x24,48x36,72x54,108x81,160x120,240x180,360x270,480x360,540x405,640x480,720x540,1080x810,1280x960&from=bu&cs=1280x960"},{"height":97,"type":"o","width":130,"url":"https:\/\/sun9-27.userapi.com\/s\/v1\/ig2\/PQTYi54nnZUU2HKekzpgw0WPjGyS_MJF5UDFTTgJXD5M02hkGQghPshhDMz1fU4AxR6h8B6KOFfrVyM2saaC50T9.jpg?quality=95&as=32x24,48x36,72x54,108x81,160x120,240x180,360x270,480x360,540x405,640x480,720x540,1080x810,1280x960&from=bu&cs=130x97"},{"height":150,"type":"p","width":200,"url":"https:\/\/sun9-27.userapi.com\/s\/v1\/ig2\/PQTYi54nnZUU2HKekzpgw0WPjGyS_MJF5UDFTTgJXD5M02hkGQghPshhDMz1fU4AxR6h8B6KOFfrVyM2saaC50T9.jpg?quality=95&as=32x24,48x36,72x54,108x81,160x120,240x180,360x270,480x360,540x405,640x480,720x540,1080x810,1280x960&from=bu&cs=200x150"},{"height":240,"type":"q","width":320,"url":"https:\/\/sun9-27.userapi.com\/s\/v1\/ig2\/PQTYi54nnZUU2HKekzpgw0WPjGyS_MJF5UDFTTgJXD5M02hkGQghPshhDMz1fU4AxR6h8B6KOFfrVyM2saaC50T9.jpg?quality=95&as=32x24,48x36,72x54,108x81,160x120,240x180,360x270,480x360,540x405,640x480,720x540,1080x810,1280x960&from=bu&cs=320x240"},{"height":382,"type":"r","width":510,"url":"https:\/\/sun9-27.userapi.com\/s\/v1\/ig2\/PQTYi54nnZUU2HKekzpgw0WPjGyS_MJF5UDFTTgJXD5M02hkGQghPshhDMz1fU4AxR6h8B6KOFfrVyM2saaC50T9.jpg?quality=95&as=32x24,48x36,72x54,108x81,160x120,240x180,360x270,480x360,540x405,640x480,720x540,1080x810,1280x960&from=bu&cs=510x382"}],"text":"","user_id":100,"web_view_token":"0de0583cdabe54e9cd","has_tags":false,"orig_photo":{"height":960,"type":"base","url":"https:\/\/sun9-27.userapi.com\/s\/v1\/ig2\/PQTYi54nnZUU2HKekzpgw0WPjGyS_MJF5UDFTTgJXD5M02hkGQghPshhDMz1fU4AxR6h8B6KOFfrVyM2saaC50T9.jpg?quality=95&as=32x24,48x36,72x54,108x81,160x120,240x180,360x270,480x360,540x405,640x480,720x540,1080x810,1280x960&from=bu","width":1280}}},{"type":"photo","photo":{"album_id":-7,"date":1743835403,"id":457273818,"owner_id":-174700694,"access_key":"f86116beb01af61e05","sizes":[{"height":75,"type":"s","width":56,"url":"https:\/\/sun9-65.userapi.com\/s\/v1\/ig2\/zDpMMTpnX_A2P4OMe4QLM_zaZDqH1G2UitXOb47vmjERo-3A9tyuIF85Eu_z3Bmn71cMq3WS1t8ssPSp2-EYZfnI.jpg?quality=95&as=32x43,48x64,72x96,108x144,160x213,240x320,360x480,480x640,540x720,640x853,720x960,960x1280&from=bu&cs=56x75"},{"height":130,"type":"m","width":97,"url":"https:\/\/sun9-65.userapi.com\/s\/v1\/ig2\/zDpMMTpnX_A2P4OMe4QLM_zaZDqH1G2UitXOb47vmjERo-3A9tyuIF85Eu_z3Bmn71cMq3WS1t8ssPSp2-EYZfnI.jpg?quality=95&as=32x43,48x64,72x96,108x144,160x213,240x320,360x480,480x640,540x720,640x853,720x960,960x1280&from=bu&cs=97x130"},{"height":604,"type":"x","width":453,"url":"https:\/\/sun9-65.userapi.com\/s\/v1\/ig2\/zDpMMTpnX_A2P4OMe4QLM_zaZDqH1G2UitXOb47vmjERo-3A9tyuIF85Eu_z3Bmn71cMq3WS1t8ssPSp2-EYZfnI.jpg?quality=95&as=32x43,48x64,72x96,108x144,160x213,240x320,360x480,480x640,540x720,640x853,720x960,960x1280&from=bu&cs=453x604"},{"height":807,"type":"y","width":605,"url":"https:\/\/sun9-65.userapi.com\/s\/v1\/ig2\/zDpMMTpnX_A2P4OMe4QLM_zaZDqH1G2UitXOb47vmjERo-3A9tyuIF85Eu_z3Bmn71cMq3WS1t8ssPSp2-EYZfnI.jpg?quality=95&as=32x43,48x64,72x96,108x144,160x213,240x320,360x480,480x640,540x720,640x853,720x960,960x1280&from=bu&cs=605x807"},{"height":1080,"type":"z","width":810,"url":"https:\/\/sun9-65.userapi.com\/s\/v1\/ig2\/zDpMMTpnX_A2P4OMe4QLM_zaZDqH1G2UitXOb47vmjERo-3A9tyuIF85Eu_z3Bmn71cMq3WS1t8ssPSp2-EYZfnI.jpg?quality=95&as=32x43,48x64,72x96,108x144,160x213,240x320,360x480,480x640,540x720,640x853,720x960,960x1280&from=bu&cs=810x1080"},{"height":1280,"type":"w","width":960,"url":"https:\/\/sun9-65.userapi.com\/s\/v1\/ig2\/zDpMMTpnX_A2P4OMe4QLM_zaZDqH1G2UitXOb47vmjERo-3A9tyuIF85Eu_z3Bmn71cMq3WS1t8ssPSp2-EYZfnI.jpg?quality=95&as=32x43,48x64,72x96,108x144,160x213,240x320,360x480,480x640,540x720,640x853,720x960,960x1280&from=bu&cs=960x1280"},{"height":173,"type":"o","width":130,"url":"https:\/\/sun9-65.userapi.com\/s\/v1\/ig2\/zDpMMTpnX_A2P4OMe4QLM_zaZDqH1G2UitXOb47vmjERo-3A9tyuIF85Eu_z3Bmn71cMq3WS1t8ssPSp2-EYZfnI.jpg?quality=95&as=32x43,48x64,72x96,108x144,160x213,240x320,360x480,480x640,540x720,640x853,720x960,960x1280&from=bu&cs=130x173"},{"height":267,"type":"p","width":200,"url":"https:\/\/sun9-65.userapi.com\/s\/v1\/ig2\/zDpMMTpnX_A2P4OMe4QLM_zaZDqH1G2UitXOb47vmjERo-3A9tyuIF85Eu_z3Bmn71cMq3WS1t8ssPSp2-EYZfnI.jpg?quality=95&as=32x43,48x64,72x96,108x144,160x213,240x320,360x480,480x640,540x720,640x853,720x960,960x1280&from=bu&cs=200x267"},{"height":427,"type":"q","width":320,"url":"https:\/\/sun9-65.userapi.com\/s\/v1\/ig2\/zDpMMTpnX_A2P4OMe4QLM_zaZDqH1G2UitXOb47vmjERo-3A9tyuIF85Eu_z3Bmn71cMq3WS1t8ssPSp2-EYZfnI.jpg?quality=95&as=32x43,48x64,72x96,108x144,160x213,240x320,360x480,480x640,540x720,640x853,720x960,960x1280&from=bu&cs=320x427"},{"height":680,"type":"r","width":510,"url":"https:\/\/sun9-65.userapi.com\/s\/v1\/ig2\/zDpMMTpnX_A2P4OMe4QLM_zaZDqH1G2UitXOb47vmjERo-3A9tyuIF85Eu_z3Bmn71cMq3WS1t8ssPSp2-EYZfnI.jpg?quality=95&as=32x43,48x64,72x96,108x144,160x213,240x320,360x480,480x640,540x720,640x853,720x960,960x1280&from=bu&cs=510x680"}],"text":"","user_id":100,"web_view_token":"c7a2718091ee84367e","has_tags":false,"orig_photo":{"height":1280,"type":"base","url":"https:\/\/sun9-65.userapi.com\/s\/v1\/ig2\/zDpMMTpnX_A2P4OMe4QLM_zaZDqH1G2UitXOb47vmjERo-3A9tyuIF85Eu_z3Bmn71cMq3WS1t8ssPSp2-EYZfnI.jpg?quality=95&as=32x43,48x64,72x96,108x144,160x213,240x320,360x480,480x640,540x720,640x853,720x960,960x1280&from=bu","width":960}}}],"date":1743835500,"from_id":-174700694,"id":8687,"likes":{"can_like":1,"count":64,"user_likes":0,"can_publish":1,"repost_disabled":false},"reaction_set_id":"reactions","reactions":{"count":64,"items":[{"id":0,"count":64}]},"owner_id":-174700694,"post_source":{"platform":"iphone","type":"api"},"post_type":"post","reposts":{"count":3,"user_reposted":0},"text":"3 и 4 апреля проходили финальные областные соревнования по волейболу среди студентов СПО Самарской области.🏐\n\nПо итогу турнира наши юноши и девушки заняли 🥈 место.\n\n❤️Поздравляем ребят и желаем им успехов в учёбе и роста спортивного мастерства.🥳","views":{"count":2123}},{"inner_type":"wall_wallpost","donut":{"is_donut":false},"comments":{"can_post":1,"can_view":1,"count":0,"groups_can_post":true},"marked_as_ads":0,"hash":"Uagejmr-nDCUjvc2xA","type":"post","push_subscription":{"is_subscribed":false},"attachments":[{"type":"video","video":{"response_type":"full","can_like":1,"can_repost":1,"can_subscribe":1,"can_add":0,"comments":0,"date":1743786767,"description":"Делимся с вами еще одним видео о том, как прошли сегодняшние мастер-классы✨\n\n#ВЧД2025 \n#Профессионалы \n#СПО\n#Профессионалы63\n#85летСПО\n#ВсероссийскоеДвижениеПрофессионалы\n#ДействуйКакПрофессионал\n#ПрофессионалыСделаноВРоссии\n#Амбассадоры_Профессионалитета #Профессионалитет\n#Первый_Педагогический #ТСПК_в_сердце","duration":40,"image":[{"url":"https:\/\/sun9-58.userapi.com\/impg\/En8YJ6F4niONwBvLoFT29FfhZqukmzaDuQZqbw\/r15Slp_9Aro.jpg?size=130x96&quality=95&keep_aspect_ratio=1&background=000000&sign=32d6a801e8c1d8736eba7ca87b90a74d&c_uniq_tag=qlhmPgkxL8mYRHm-QWj8hLr31fpvVUEg_aghs3eRhpU&type=video_thumb","width":130,"height":96,"with_padding":1},{"url":"https:\/\/sun9-58.userapi.com\/impg\/En8YJ6F4niONwBvLoFT29FfhZqukmzaDuQZqbw\/r15Slp_9Aro.jpg?size=160x120&quality=95&keep_aspect_ratio=1&background=000000&sign=69fd754a134a6199ad8be7980d27a126&c_uniq_tag=ZQOPqCoZXOpc4sxPhWOY4M50HkNFLkwkJfwBjjU03C4&type=video_thumb","width":160,"height":120,"with_padding":1},{"url":"https:\/\/sun9-58.userapi.com\/impg\/En8YJ6F4niONwBvLoFT29FfhZqukmzaDuQZqbw\/r15Slp_9Aro.jpg?size=320x240&quality=95&keep_aspect_ratio=1&background=000000&sign=2ebb50cd01ec6dbed99ca2f4151e58df&c_uniq_tag=M3q6kGDmNnfgzFfSXhnHBaROe1Ur1tTHoo5NkcOfPqM&type=video_thumb","width":320,"height":240,"with_padding":1},{"url":"https:\/\/sun9-58.userapi.com\/impg\/En8YJ6F4niONwBvLoFT29FfhZqukmzaDuQZqbw\/r15Slp_9Aro.jpg?size=800x450&quality=95&keep_aspect_ratio=1&background=000000&sign=8a2ada4967828d4a8e29f9bf1cd144a8&c_uniq_tag=LsiiSk9woc7YZJf34trrwpVNBFYoZk8GKjV8MFTQhJI&type=video_thumb","width":800,"height":450,"with_padding":1},{"url":"https:\/\/sun9-58.userapi.com\/impg\/En8YJ6F4niONwBvLoFT29FfhZqukmzaDuQZqbw\/r15Slp_9Aro.jpg?size=405x720&quality=95&sign=df093891a78dc9327c1efe129b46053f&c_uniq_tag=RvtMSWQnUZncYP3bxhVIxXQrFr9Msy9sk94dU6mHya4&type=video_thumb","width":405,"height":720},{"url":"https:\/\/sun9-58.userapi.com\/impg\/En8YJ6F4niONwBvLoFT29FfhZqukmzaDuQZqbw\/r15Slp_9Aro.jpg?size=360x640&quality=95&sign=9f65168de9972989214767a165c3f02c&c_uniq_tag=CNxUm3SMGsAM7ER164a0FYpx8lFOOm1Py2htELAEnHU&type=video_thumb","width":360,"height":640},{"url":"https:\/\/sun9-58.userapi.com\/impg\/En8YJ6F4niONwBvLoFT29FfhZqukmzaDuQZqbw\/r15Slp_9Aro.jpg?size=420x746&quality=95&sign=508b4ca370b2bacaa834102bd99a4518&c_uniq_tag=8uTu9Muw4BCK2k22o9MfC32IJoBiqaSDUPGoMujiLsQ&type=video_thumb","width":420,"height":746},{"url":"https:\/\/sun9-58.userapi.com\/impg\/En8YJ6F4niONwBvLoFT29FfhZqukmzaDuQZqbw\/r15Slp_9Aro.jpg?size=420x746&quality=95&sign=508b4ca370b2bacaa834102bd99a4518&c_uniq_tag=8uTu9Muw4BCK2k22o9MfC32IJoBiqaSDUPGoMujiLsQ&type=video_thumb","width":420,"height":746},{"url":"https:\/\/sun9-58.userapi.com\/impg\/En8YJ6F4niONwBvLoFT29FfhZqukmzaDuQZqbw\/r15Slp_9Aro.jpg?quality=90&proxy=1&sign=667ae1d3a4399008020392578c15a14e&c_uniq_tag=TBsk_WMlpAL_FuyndOiUrcJ2TDpQJmpNjvXsmu8lQB8&type=video_thumb","width":420,"height":746}],"first_frame":[{"url":"https:\/\/i.mycdn.me\/getVideoPreview?id=8364331633294&idx=0&type=32&tkn=ZFsGe2LtEd91jv-SmzAU49YDSgc","width":405,"height":720},{"url":"https:\/\/i.mycdn.me\/getVideoPreview?id=8364331633294&idx=0&type=33&tkn=A2aJrhn4xVJtFCGth0bcp-JyMqc","width":270,"height":480},{"url":"https:\/\/i.mycdn.me\/getVideoPreview?id=8364331633294&idx=0&type=34&tkn=fks7lN45-R7Sp551wV7wnI9pdKE","width":135,"height":240},{"url":"https:\/\/i.mycdn.me\/getVideoPreview?id=8364331633294&idx=0&type=35&tkn=roD9mdudbwmgrVe6zONwhxaPeIg","width":72,"height":128},{"url":"https:\/\/i.mycdn.me\/getVideoPreview?id=8364331633294&idx=0&type=37&tkn=QDjlcxjHxtlJSfK1A-X19WTloVU","width":720,"height":1280},{"url":"https:\/\/i.mycdn.me\/getVideoPreview?id=8364331633294&idx=0&type=38&tkn=dQBwiwJbbgrBpAlhqVufwP97qIM","width":540,"height":960},{"url":"https:\/\/i.mycdn.me\/getVideoPreview?id=8364331633294&idx=0&type=39&tkn=4BzsjmmBplOnDPgiQ-UxxO2Qxcc","width":720,"height":1280},{"url":"https:\/\/i.mycdn.me\/getVideoPreview?id=8364331633294&idx=0&type=43&tkn=i9irmzEFqN1MQNzoHK6FfOTafvE","width":1080,"height":1920}],"width":2160,"height":3840,"id":456240416,"owner_id":-174700694,"title":"Clip by @tspk63","track_code":"video_5ea4b8b102kRYsqTJYOpdsj01J5TmabMPgzuKDQbPnC7zM7RmrPfUA1kyZAig695xZ-znF6alPgOON8eMGxUjVEvS7T239B9PFP9pxKzmUAOP3RVmVBrB_E5","repeat":1,"type":"short_video","views":926,"local_views":926,"can_dislike":1,"wall_post_id":8685,"should_stretch":false}}],"date":1743787290,"from_id":-174700694,"id":8685,"likes":{"can_like":1,"count":29,"user_likes":0,"can_publish":1,"repost_disabled":false},"reaction_set_id":"reactions","reactions":{"count":29,"items":[{"id":0,"count":29}]},"owner_id":-174700694,"post_source":{"type":"vk"},"post_type":"post","reposts":{"count":0,"user_reposted":0},"text":"","views":{"count":972}},{"inner_type":"wall_wallpost","donut":{"is_donut":false},"check_sign":true,"comments":{"can_post":1,"can_view":1,"count":0,"groups_can_post":true},"marked_as_ads":0,"hash":"UGUxbmK1H0s7aFR9eg","type":"post","push_subscription":{"is_subscribed":false},"attachments":[{"type":"photo","photo":{"album_id":-7,"date":1743789166,"id":457273808,"owner_id":-174700694,"access_key":"d5639659921a2072aa","sizes":[{"height":43,"type":"s","width":75,"url":"https:\/\/sun9-8.userapi.com\/s\/v1\/ig2\/L0RJjhC6gta7W1SfrIMdthUIjumz_bUMPb5Y-aHoeQr0WPcU6HN9WvQS8aE5DIs52faj9X39OYEhbXz3FK1Vqi8f.jpg?quality=95&as=32x18,48x28,72x41,108x62,160x92,240x138,360x206,480x275,540x310,640x367,720x413,1080x620,1280x734,1440x826,2526x1449&from=bu&cs=75x43"},{"height":75,"type":"m","width":130,"url":"https:\/\/sun9-8.userapi.com\/s\/v1\/ig2\/L0RJjhC6gta7W1SfrIMdthUIjumz_bUMPb5Y-aHoeQr0WPcU6HN9WvQS8aE5DIs52faj9X39OYEhbXz3FK1Vqi8f.jpg?quality=95&as=32x18,48x28,72x41,108x62,160x92,240x138,360x206,480x275,540x310,640x367,720x413,1080x620,1280x734,1440x826,2526x1449&from=bu&cs=130x75"},{"height":346,"type":"x","width":604,"url":"https:\/\/sun9-8.userapi.com\/s\/v1\/ig2\/L0RJjhC6gta7W1SfrIMdthUIjumz_bUMPb5Y-aHoeQr0WPcU6HN9WvQS8aE5DIs52faj9X39OYEhbXz3FK1Vqi8f.jpg?quality=95&as=32x18,48x28,72x41,108x62,160x92,240x138,360x206,480x275,540x310,640x367,720x413,1080x620,1280x734,1440x826,2526x1449&from=bu&cs=604x346"},{"height":463,"type":"y","width":807,"url":"https:\/\/sun9-8.userapi.com\/s\/v1\/ig2\/L0RJjhC6gta7W1SfrIMdthUIjumz_bUMPb5Y-aHoeQr0WPcU6HN9WvQS8aE5DIs52faj9X39OYEhbXz3FK1Vqi8f.jpg?quality=95&as=32x18,48x28,72x41,108x62,160x92,240x138,360x206,480x275,540x310,640x367,720x413,1080x620,1280x734,1440x826,2526x1449&from=bu&cs=807x463"},{"height":734,"type":"z","width":1280,"url":"https:\/\/sun9-8.userapi.com\/s\/v1\/ig2\/L0RJjhC6gta7W1SfrIMdthUIjumz_bUMPb5Y-aHoeQr0WPcU6HN9WvQS8aE5DIs52faj9X39OYEhbXz3FK1Vqi8f.jpg?quality=95&as=32x18,48x28,72x41,108x62,160x92,240x138,360x206,480x275,540x310,640x367,720x413,1080x620,1280x734,1440x826,2526x1449&from=bu&cs=1280x734"},{"height":1449,"type":"w","width":2526,"url":"https:\/\/sun9-8.userapi.com\/s\/v1\/ig2\/L0RJjhC6gta7W1SfrIMdthUIjumz_bUMPb5Y-aHoeQr0WPcU6HN9WvQS8aE5DIs52faj9X39OYEhbXz3FK1Vqi8f.jpg?quality=95&as=32x18,48x28,72x41,108x62,160x92,240x138,360x206,480x275,540x310,640x367,720x413,1080x620,1280x734,1440x826,2526x1449&from=bu&cs=2526x1449"},{"height":87,"type":"o","width":130,"url":"https:\/\/sun9-8.userapi.com\/s\/v1\/ig2\/L0RJjhC6gta7W1SfrIMdthUIjumz_bUMPb5Y-aHoeQr0WPcU6HN9WvQS8aE5DIs52faj9X39OYEhbXz3FK1Vqi8f.jpg?quality=95&as=32x18,48x28,72x41,108x62,160x92,240x138,360x206,480x275,540x310,640x367,720x413,1080x620,1280x734,1440x826,2526x1449&from=bu&cs=130x87"},{"height":133,"type":"p","width":200,"url":"https:\/\/sun9-8.userapi.com\/s\/v1\/ig2\/L0RJjhC6gta7W1SfrIMdthUIjumz_bUMPb5Y-aHoeQr0WPcU6HN9WvQS8aE5DIs52faj9X39OYEhbXz3FK1Vqi8f.jpg?quality=95&as=32x18,48x28,72x41,108x62,160x92,240x138,360x206,480x275,540x310,640x367,720x413,1080x620,1280x734,1440x826,2526x1449&from=bu&cs=200x133"},{"height":213,"type":"q","width":320,"url":"https:\/\/sun9-8.userapi.com\/s\/v1\/ig2\/L0RJjhC6gta7W1SfrIMdthUIjumz_bUMPb5Y-aHoeQr0WPcU6HN9WvQS8aE5DIs52faj9X39OYEhbXz3FK1Vqi8f.jpg?quality=95&as=32x18,48x28,72x41,108x62,160x92,240x138,360x206,480x275,540x310,640x367,720x413,1080x620,1280x734,1440x826,2526x1449&from=bu&cs=320x213"},{"height":340,"type":"r","width":510,"url":"https:\/\/sun9-8.userapi.com\/s\/v1\/ig2\/L0RJjhC6gta7W1SfrIMdthUIjumz_bUMPb5Y-aHoeQr0WPcU6HN9WvQS8aE5DIs52faj9X39OYEhbXz3FK1Vqi8f.jpg?quality=95&as=32x18,48x28,72x41,108x62,160x92,240x138,360x206,480x275,540x310,640x367,720x413,1080x620,1280x734,1440x826,2526x1449&from=bu&cs=510x340"}],"text":"","user_id":100,"web_view_token":"ae419b7eda1292e2d3","has_tags":false,"orig_photo":{"height":1449,"type":"base","url":"https:\/\/sun9-8.userapi.com\/s\/v1\/ig2\/L0RJjhC6gta7W1SfrIMdthUIjumz_bUMPb5Y-aHoeQr0WPcU6HN9WvQS8aE5DIs52faj9X39OYEhbXz3FK1Vqi8f.jpg?quality=95&as=32x18,48x28,72x41,108x62,160x92,240x138,360x206,480x275,540x310,640x367,720x413,1080x620,1280x734,1440x826,2526x1449&from=bu","width":2526}}}],"date":1743773208,"edited":1743789166,"from_id":-174700694,"id":8684,"likes":{"can_like":1,"count":13,"user_likes":0,"can_publish":1,"repost_disabled":false},"reaction_set_id":"reactions","reactions":{"count":13,"items":[{"id":0,"count":13}]},"owner_id":-174700694,"post_source":{"platform":"iphone","type":"api"},"post_type":"post","reposts":{"count":3,"user_reposted":0},"text":"Уважаемые родители! Пришло время нам с вами встретиться. \n\nПриглашаем Вас на родительское собрание 08.04.2025 года в 18.30 онлайн. Продолжительность собрания 1 ч.-1ч15мин. \n\n Вопросы для встречи: \n1. «Профилактика преступлений несовершеннолетних в сфере незаконного оборота наркотиков, а также вовлечение несовершеннолетних в совершение противоправных деяний с использованием компьютерных технологий». (Педагог- психолог Желнова М.М.)\n2. Прикладные знания по теме: «Как слушать и услышать своего ребенка». \n3. Ответы на вопросы родителей. \nДля подключения к встрече – необходимо пройти по ссылке. \nhttps:\/\/bbb.tspk.org\/b\/fgu-7ac-utp-lxx \n \nПо этой ссылке – заполнив форму, вы можете задать заранее вопрос. А на собрании - я дам вам развернутый ответ. \nhttps:\/\/docs.google.com\/forms\/d\/e\/1FAIpQLSdlPIa1xDehp_60SBBOJ_pVvG3h7VKVW5QzckKUiIgxHE5uVw\/viewform","views":{"count":751}},{"inner_type":"wall_wallpost","donut":{"is_donut":false},"comments":{"can_post":1,"can_view":1,"count":0,"groups_can_post":true},"marked_as_ads":0,"hash":"73vDa11llhiapr1VRA","type":"post","push_subscription":{"is_subscribed":false},"carousel_offset":0,"attachments":[{"type":"photo","photo":{"album_id":-7,"date":1743773171,"id":457273803,"owner_id":-174700694,"access_key":"3c1f5c202cd3a8fa4e","sizes":[{"height":56,"type":"s","width":75,"url":"https:\/\/sun9-22.userapi.com\/s\/v1\/ig2\/DWOOioRXW_njC87KiJoyjIbZZidSvKA0kCs6X1OxgGH4LQ2fG9vug54O2g9Ye0X-u7nHSiH62Shc7U1fyT9xAi0A.jpg?quality=95&as=32x24,48x36,72x54,108x81,160x120,240x180,360x270,480x360,540x405,640x480,720x540,1080x810,1280x960&from=bu&cs=75x56"},{"height":97,"type":"m","width":130,"url":"https:\/\/sun9-22.userapi.com\/s\/v1\/ig2\/DWOOioRXW_njC87KiJoyjIbZZidSvKA0kCs6X1OxgGH4LQ2fG9vug54O2g9Ye0X-u7nHSiH62Shc7U1fyT9xAi0A.jpg?quality=95&as=32x24,48x36,72x54,108x81,160x120,240x180,360x270,480x360,540x405,640x480,720x540,1080x810,1280x960&from=bu&cs=130x97"},{"height":453,"type":"x","width":604,"url":"https:\/\/sun9-22.userapi.com\/s\/v1\/ig2\/DWOOioRXW_njC87KiJoyjIbZZidSvKA0kCs6X1OxgGH4LQ2fG9vug54O2g9Ye0X-u7nHSiH62Shc7U1fyT9xAi0A.jpg?quality=95&as=32x24,48x36,72x54,108x81,160x120,240x180,360x270,480x360,540x405,640x480,720x540,1080x810,1280x960&from=bu&cs=604x453"},{"height":605,"type":"y","width":807,"url":"https:\/\/sun9-22.userapi.com\/s\/v1\/ig2\/DWOOioRXW_njC87KiJoyjIbZZidSvKA0kCs6X1OxgGH4LQ2fG9vug54O2g9Ye0X-u7nHSiH62Shc7U1fyT9xAi0A.jpg?quality=95&as=32x24,48x36,72x54,108x81,160x120,240x180,360x270,480x360,540x405,640x480,720x540,1080x810,1280x960&from=bu&cs=807x605"},{"height":960,"type":"z","width":1280,"url":"https:\/\/sun9-22.userapi.com\/s\/v1\/ig2\/DWOOioRXW_njC87KiJoyjIbZZidSvKA0kCs6X1OxgGH4LQ2fG9vug54O2g9Ye0X-u7nHSiH62Shc7U1fyT9xAi0A.jpg?quality=95&as=32x24,48x36,72x54,108x81,160x120,240x180,360x270,480x360,540x405,640x480,720x540,1080x810,1280x960&from=bu&cs=1280x960"},{"height":97,"type":"o","width":130,"url":"https:\/\/sun9-22.userapi.com\/s\/v1\/ig2\/DWOOioRXW_njC87KiJoyjIbZZidSvKA0kCs6X1OxgGH4LQ2fG9vug54O2g9Ye0X-u7nHSiH62Shc7U1fyT9xAi0A.jpg?quality=95&as=32x24,48x36,72x54,108x81,160x120,240x180,360x270,480x360,540x405,640x480,720x540,1080x810,1280x960&from=bu&cs=130x97"},{"height":150,"type":"p","width":200,"url":"https:\/\/sun9-22.userapi.com\/s\/v1\/ig2\/DWOOioRXW_njC87KiJoyjIbZZidSvKA0kCs6X1OxgGH4LQ2fG9vug54O2g9Ye0X-u7nHSiH62Shc7U1fyT9xAi0A.jpg?quality=95&as=32x24,48x36,72x54,108x81,160x120,240x180,360x270,480x360,540x405,640x480,720x540,1080x810,1280x960&from=bu&cs=200x150"},{"height":240,"type":"q","width":320,"url":"https:\/\/sun9-22.userapi.com\/s\/v1\/ig2\/DWOOioRXW_njC87KiJoyjIbZZidSvKA0kCs6X1OxgGH4LQ2fG9vug54O2g9Ye0X-u7nHSiH62Shc7U1fyT9xAi0A.jpg?quality=95&as=32x24,48x36,72x54,108x81,160x120,240x180,360x270,480x360,540x405,640x480,720x540,1080x810,1280x960&from=bu&cs=320x240"},{"height":382,"type":"r","width":510,"url":"https:\/\/sun9-22.userapi.com\/s\/v1\/ig2\/DWOOioRXW_njC87KiJoyjIbZZidSvKA0kCs6X1OxgGH4LQ2fG9vug54O2g9Ye0X-u7nHSiH62Shc7U1fyT9xAi0A.jpg?quality=95&as=32x24,48x36,72x54,108x81,160x120,240x180,360x270,480x360,540x405,640x480,720x540,1080x810,1280x960&from=bu&cs=510x382"}],"text":"","user_id":100,"web_view_token":"d599c04ace342c42c3","has_tags":false,"orig_photo":{"height":960,"type":"base","url":"https:\/\/sun9-22.userapi.com\/s\/v1\/ig2\/DWOOioRXW_njC87KiJoyjIbZZidSvKA0kCs6X1OxgGH4LQ2fG9vug54O2g9Ye0X-u7nHSiH62Shc7U1fyT9xAi0A.jpg?quality=95&as=32x24,48x36,72x54,108x81,160x120,240x180,360x270,480x360,540x405,640x480,720x540,1080x810,1280x960&from=bu","width":1280}}},{"type":"photo","photo":{"album_id":-7,"date":1743773171,"id":457273804,"owner_id":-174700694,"access_key":"917d70d2e25a43db74","sizes":[{"height":56,"type":"s","width":75,"url":"https:\/\/sun9-1.userapi.com\/s\/v1\/ig2\/3INpQ-Z3hufZvnVxfl1ntEu9bT4vt3lPcWm5Vxn-XN_MknIRXeTu9Qtf5P3J7an-_bt6pH4huTcxuEWUZ4nsd-bp.jpg?quality=95&as=32x24,48x36,72x54,108x81,160x120,240x180,360x270,480x360,540x405,640x480,720x540,1080x810,1280x960&from=bu&cs=75x56"},{"height":97,"type":"m","width":130,"url":"https:\/\/sun9-1.userapi.com\/s\/v1\/ig2\/3INpQ-Z3hufZvnVxfl1ntEu9bT4vt3lPcWm5Vxn-XN_MknIRXeTu9Qtf5P3J7an-_bt6pH4huTcxuEWUZ4nsd-bp.jpg?quality=95&as=32x24,48x36,72x54,108x81,160x120,240x180,360x270,480x360,540x405,640x480,720x540,1080x810,1280x960&from=bu&cs=130x97"},{"height":453,"type":"x","width":604,"url":"https:\/\/sun9-1.userapi.com\/s\/v1\/ig2\/3INpQ-Z3hufZvnVxfl1ntEu9bT4vt3lPcWm5Vxn-XN_MknIRXeTu9Qtf5P3J7an-_bt6pH4huTcxuEWUZ4nsd-bp.jpg?quality=95&as=32x24,48x36,72x54,108x81,160x120,240x180,360x270,480x360,540x405,640x480,720x540,1080x810,1280x960&from=bu&cs=604x453"},{"height":605,"type":"y","width":807,"url":"https:\/\/sun9-1.userapi.com\/s\/v1\/ig2\/3INpQ-Z3hufZvnVxfl1ntEu9bT4vt3lPcWm5Vxn-XN_MknIRXeTu9Qtf5P3J7an-_bt6pH4huTcxuEWUZ4nsd-bp.jpg?quality=95&as=32x24,48x36,72x54,108x81,160x120,240x180,360x270,480x360,540x405,640x480,720x540,1080x810,1280x960&from=bu&cs=807x605"},{"height":960,"type":"z","width":1280,"url":"https:\/\/sun9-1.userapi.com\/s\/v1\/ig2\/3INpQ-Z3hufZvnVxfl1ntEu9bT4vt3lPcWm5Vxn-XN_MknIRXeTu9Qtf5P3J7an-_bt6pH4huTcxuEWUZ4nsd-bp.jpg?quality=95&as=32x24,48x36,72x54,108x81,160x120,240x180,360x270,480x360,540x405,640x480,720x540,1080x810,1280x960&from=bu&cs=1280x960"},{"height":97,"type":"o","width":130,"url":"https:\/\/sun9-1.userapi.com\/s\/v1\/ig2\/3INpQ-Z3hufZvnVxfl1ntEu9bT4vt3lPcWm5Vxn-XN_MknIRXeTu9Qtf5P3J7an-_bt6pH4huTcxuEWUZ4nsd-bp.jpg?quality=95&as=32x24,48x36,72x54,108x81,160x120,240x180,360x270,480x360,540x405,640x480,720x540,1080x810,1280x960&from=bu&cs=130x97"},{"height":150,"type":"p","width":200,"url":"https:\/\/sun9-1.userapi.com\/s\/v1\/ig2\/3INpQ-Z3hufZvnVxfl1ntEu9bT4vt3lPcWm5Vxn-XN_MknIRXeTu9Qtf5P3J7an-_bt6pH4huTcxuEWUZ4nsd-bp.jpg?quality=95&as=32x24,48x36,72x54,108x81,160x120,240x180,360x270,480x360,540x405,640x480,720x540,1080x810,1280x960&from=bu&cs=200x150"},{"height":240,"type":"q","width":320,"url":"https:\/\/sun9-1.userapi.com\/s\/v1\/ig2\/3INpQ-Z3hufZvnVxfl1ntEu9bT4vt3lPcWm5Vxn-XN_MknIRXeTu9Qtf5P3J7an-_bt6pH4huTcxuEWUZ4nsd-bp.jpg?quality=95&as=32x24,48x36,72x54,108x81,160x120,240x180,360x270,480x360,540x405,640x480,720x540,1080x810,1280x960&from=bu&cs=320x240"},{"height":382,"type":"r","width":510,"url":"https:\/\/sun9-1.userapi.com\/s\/v1\/ig2\/3INpQ-Z3hufZvnVxfl1ntEu9bT4vt3lPcWm5Vxn-XN_MknIRXeTu9Qtf5P3J7an-_bt6pH4huTcxuEWUZ4nsd-bp.jpg?quality=95&as=32x24,48x36,72x54,108x81,160x120,240x180,360x270,480x360,540x405,640x480,720x540,1080x810,1280x960&from=bu&cs=510x382"}],"text":"","user_id":100,"web_view_token":"4fc842f462f9dda731","has_tags":false,"orig_photo":{"height":960,"type":"base","url":"https:\/\/sun9-1.userapi.com\/s\/v1\/ig2\/3INpQ-Z3hufZvnVxfl1ntEu9bT4vt3lPcWm5Vxn-XN_MknIRXeTu9Qtf5P3J7an-_bt6pH4huTcxuEWUZ4nsd-bp.jpg?quality=95&as=32x24,48x36,72x54,108x81,160x120,240x180,360x270,480x360,540x405,640x480,720x540,1080x810,1280x960&from=bu","width":1280}}},{"type":"photo","photo":{"album_id":-7,"date":1743773171,"id":457273805,"owner_id":-174700694,"access_key":"4f661d8624c6befe27","sizes":[{"height":56,"type":"s","width":75,"url":"https:\/\/sun9-12.userapi.com\/s\/v1\/ig2\/McdQE_JL6wKyQ4PRypXpqb9N3uP_ITkjIWMJR1NYZ2xjKoDddgD_0In0vw_AQCLVgYFviVW2ljTv3Z_7pJv2Qm4d.jpg?quality=95&as=32x24,48x36,72x54,108x81,160x120,240x180,360x270,480x360,540x405,640x480,720x540,1080x810,1280x960&from=bu&cs=75x56"},{"height":97,"type":"m","width":130,"url":"https:\/\/sun9-12.userapi.com\/s\/v1\/ig2\/McdQE_JL6wKyQ4PRypXpqb9N3uP_ITkjIWMJR1NYZ2xjKoDddgD_0In0vw_AQCLVgYFviVW2ljTv3Z_7pJv2Qm4d.jpg?quality=95&as=32x24,48x36,72x54,108x81,160x120,240x180,360x270,480x360,540x405,640x480,720x540,1080x810,1280x960&from=bu&cs=130x97"},{"height":453,"type":"x","width":604,"url":"https:\/\/sun9-12.userapi.com\/s\/v1\/ig2\/McdQE_JL6wKyQ4PRypXpqb9N3uP_ITkjIWMJR1NYZ2xjKoDddgD_0In0vw_AQCLVgYFviVW2ljTv3Z_7pJv2Qm4d.jpg?quality=95&as=32x24,48x36,72x54,108x81,160x120,240x180,360x270,480x360,540x405,640x480,720x540,1080x810,1280x960&from=bu&cs=604x453"},{"height":605,"type":"y","width":807,"url":"https:\/\/sun9-12.userapi.com\/s\/v1\/ig2\/McdQE_JL6wKyQ4PRypXpqb9N3uP_ITkjIWMJR1NYZ2xjKoDddgD_0In0vw_AQCLVgYFviVW2ljTv3Z_7pJv2Qm4d.jpg?quality=95&as=32x24,48x36,72x54,108x81,160x120,240x180,360x270,480x360,540x405,640x480,720x540,1080x810,1280x960&from=bu&cs=807x605"},{"height":960,"type":"z","width":1280,"url":"https:\/\/sun9-12.userapi.com\/s\/v1\/ig2\/McdQE_JL6wKyQ4PRypXpqb9N3uP_ITkjIWMJR1NYZ2xjKoDddgD_0In0vw_AQCLVgYFviVW2ljTv3Z_7pJv2Qm4d.jpg?quality=95&as=32x24,48x36,72x54,108x81,160x120,240x180,360x270,480x360,540x405,640x480,720x540,1080x810,1280x960&from=bu&cs=1280x960"},{"height":97,"type":"o","width":130,"url":"https:\/\/sun9-12.userapi.com\/s\/v1\/ig2\/McdQE_JL6wKyQ4PRypXpqb9N3uP_ITkjIWMJR1NYZ2xjKoDddgD_0In0vw_AQCLVgYFviVW2ljTv3Z_7pJv2Qm4d.jpg?quality=95&as=32x24,48x36,72x54,108x81,160x120,240x180,360x270,480x360,540x405,640x480,720x540,1080x810,1280x960&from=bu&cs=130x97"},{"height":150,"type":"p","width":200,"url":"https:\/\/sun9-12.userapi.com\/s\/v1\/ig2\/McdQE_JL6wKyQ4PRypXpqb9N3uP_ITkjIWMJR1NYZ2xjKoDddgD_0In0vw_AQCLVgYFviVW2ljTv3Z_7pJv2Qm4d.jpg?quality=95&as=32x24,48x36,72x54,108x81,160x120,240x180,360x270,480x360,540x405,640x480,720x540,1080x810,1280x960&from=bu&cs=200x150"},{"height":240,"type":"q","width":320,"url":"https:\/\/sun9-12.userapi.com\/s\/v1\/ig2\/McdQE_JL6wKyQ4PRypXpqb9N3uP_ITkjIWMJR1NYZ2xjKoDddgD_0In0vw_AQCLVgYFviVW2ljTv3Z_7pJv2Qm4d.jpg?quality=95&as=32x24,48x36,72x54,108x81,160x120,240x180,360x270,480x360,540x405,640x480,720x540,1080x810,1280x960&from=bu&cs=320x240"},{"height":382,"type":"r","width":510,"url":"https:\/\/sun9-12.userapi.com\/s\/v1\/ig2\/McdQE_JL6wKyQ4PRypXpqb9N3uP_ITkjIWMJR1NYZ2xjKoDddgD_0In0vw_AQCLVgYFviVW2ljTv3Z_7pJv2Qm4d.jpg?quality=95&as=32x24,48x36,72x54,108x81,160x120,240x180,360x270,480x360,540x405,640x480,720x540,1080x810,1280x960&from=bu&cs=510x382"}],"text":"","user_id":100,"web_view_token":"2567ecd1f42577297c","has_tags":false,"orig_photo":{"height":960,"type":"base","url":"https:\/\/sun9-12.userapi.com\/s\/v1\/ig2\/McdQE_JL6wKyQ4PRypXpqb9N3uP_ITkjIWMJR1NYZ2xjKoDddgD_0In0vw_AQCLVgYFviVW2ljTv3Z_7pJv2Qm4d.jpg?quality=95&as=32x24,48x36,72x54,108x81,160x120,240x180,360x270,480x360,540x405,640x480,720x540,1080x810,1280x960&from=bu","width":1280}}},{"type":"photo","photo":{"album_id":-7,"date":1743773171,"id":457273806,"owner_id":-174700694,"access_key":"b068be6cabebfa74d2","sizes":[{"height":56,"type":"s","width":75,"url":"https:\/\/sun9-16.userapi.com\/s\/v1\/ig2\/TemYH9DaoLVtEkeASAmaIOTr7Mwh1zVKsUo58-X_cxstIyXzgdFZisElQh9mSqnlecKiZx2W-9HHWJaWAnZlMXre.jpg?quality=95&as=32x24,48x36,72x54,108x81,160x120,240x180,360x270,480x360,540x405,640x480,720x540,1080x810,1280x960,1440x1080,2560x1920&from=bu&cs=75x56"},{"height":97,"type":"m","width":130,"url":"https:\/\/sun9-16.userapi.com\/s\/v1\/ig2\/TemYH9DaoLVtEkeASAmaIOTr7Mwh1zVKsUo58-X_cxstIyXzgdFZisElQh9mSqnlecKiZx2W-9HHWJaWAnZlMXre.jpg?quality=95&as=32x24,48x36,72x54,108x81,160x120,240x180,360x270,480x360,540x405,640x480,720x540,1080x810,1280x960,1440x1080,2560x1920&from=bu&cs=130x97"},{"height":453,"type":"x","width":604,"url":"https:\/\/sun9-16.userapi.com\/s\/v1\/ig2\/TemYH9DaoLVtEkeASAmaIOTr7Mwh1zVKsUo58-X_cxstIyXzgdFZisElQh9mSqnlecKiZx2W-9HHWJaWAnZlMXre.jpg?quality=95&as=32x24,48x36,72x54,108x81,160x120,240x180,360x270,480x360,540x405,640x480,720x540,1080x810,1280x960,1440x1080,2560x1920&from=bu&cs=604x453"},{"height":605,"type":"y","width":807,"url":"https:\/\/sun9-16.userapi.com\/s\/v1\/ig2\/TemYH9DaoLVtEkeASAmaIOTr7Mwh1zVKsUo58-X_cxstIyXzgdFZisElQh9mSqnlecKiZx2W-9HHWJaWAnZlMXre.jpg?quality=95&as=32x24,48x36,72x54,108x81,160x120,240x180,360x270,480x360,540x405,640x480,720x540,1080x810,1280x960,1440x1080,2560x1920&from=bu&cs=807x605"},{"height":960,"type":"z","width":1280,"url":"https:\/\/sun9-16.userapi.com\/s\/v1\/ig2\/TemYH9DaoLVtEkeASAmaIOTr7Mwh1zVKsUo58-X_cxstIyXzgdFZisElQh9mSqnlecKiZx2W-9HHWJaWAnZlMXre.jpg?quality=95&as=32x24,48x36,72x54,108x81,160x120,240x180,360x270,480x360,540x405,640x480,720x540,1080x810,1280x960,1440x1080,2560x1920&from=bu&cs=1280x960"},{"height":1920,"type":"w","width":2560,"url":"https:\/\/sun9-16.userapi.com\/s\/v1\/ig2\/TemYH9DaoLVtEkeASAmaIOTr7Mwh1zVKsUo58-X_cxstIyXzgdFZisElQh9mSqnlecKiZx2W-9HHWJaWAnZlMXre.jpg?quality=95&as=32x24,48x36,72x54,108x81,160x120,240x180,360x270,480x360,540x405,640x480,720x540,1080x810,1280x960,1440x1080,2560x1920&from=bu&cs=2560x1920"},{"height":97,"type":"o","width":130,"url":"https:\/\/sun9-16.userapi.com\/s\/v1\/ig2\/TemYH9DaoLVtEkeASAmaIOTr7Mwh1zVKsUo58-X_cxstIyXzgdFZisElQh9mSqnlecKiZx2W-9HHWJaWAnZlMXre.jpg?quality=95&as=32x24,48x36,72x54,108x81,160x120,240x180,360x270,480x360,540x405,640x480,720x540,1080x810,1280x960,1440x1080,2560x1920&from=bu&cs=130x97"},{"height":150,"type":"p","width":200,"url":"https:\/\/sun9-16.userapi.com\/s\/v1\/ig2\/TemYH9DaoLVtEkeASAmaIOTr7Mwh1zVKsUo58-X_cxstIyXzgdFZisElQh9mSqnlecKiZx2W-9HHWJaWAnZlMXre.jpg?quality=95&as=32x24,48x36,72x54,108x81,160x120,240x180,360x270,480x360,540x405,640x480,720x540,1080x810,1280x960,1440x1080,2560x1920&from=bu&cs=200x150"},{"height":240,"type":"q","width":320,"url":"https:\/\/sun9-16.userapi.com\/s\/v1\/ig2\/TemYH9DaoLVtEkeASAmaIOTr7Mwh1zVKsUo58-X_cxstIyXzgdFZisElQh9mSqnlecKiZx2W-9HHWJaWAnZlMXre.jpg?quality=95&as=32x24,48x36,72x54,108x81,160x120,240x180,360x270,480x360,540x405,640x480,720x540,1080x810,1280x960,1440x1080,2560x1920&from=bu&cs=320x240"},{"height":382,"type":"r","width":510,"url":"https:\/\/sun9-16.userapi.com\/s\/v1\/ig2\/TemYH9DaoLVtEkeASAmaIOTr7Mwh1zVKsUo58-X_cxstIyXzgdFZisElQh9mSqnlecKiZx2W-9HHWJaWAnZlMXre.jpg?quality=95&as=32x24,48x36,72x54,108x81,160x120,240x180,360x270,480x360,540x405,640x480,720x540,1080x810,1280x960,1440x1080,2560x1920&from=bu&cs=510x382"}],"text":"","user_id":100,"web_view_token":"881a929e283d811059","has_tags":false,"orig_photo":{"height":1920,"type":"base","url":"https:\/\/sun9-16.userapi.com\/s\/v1\/ig2\/TemYH9DaoLVtEkeASAmaIOTr7Mwh1zVKsUo58-X_cxstIyXzgdFZisElQh9mSqnlecKiZx2W-9HHWJaWAnZlMXre.jpg?quality=95&as=32x24,48x36,72x54,108x81,160x120,240x180,360x270,480x360,540x405,640x480,720x540,1080x810,1280x960,1440x1080,2560x1920&from=bu","width":2560}}}],"date":1743773172,"from_id":-174700694,"id":8683,"likes":{"can_like":1,"count":13,"user_likes":0,"can_publish":1,"repost_disabled":false},"reaction_set_id":"reactions","reactions":{"count":13,"items":[{"id":0,"count":13}]},"owner_id":-174700694,"post_source":{"platform":"iphone","type":"api"},"post_type":"post","reposts":{"count":0,"user_reposted":0},"text":"В рамках Всероссийской акции: \"Сообщи, где торгуют смертью\" в ГАПОУ ТСПК были проведены профилактические беседы педагогом-психологом Жуковой В.В. с обучающимися группы ИСиП-13, ИСиП-23, ИСиП-32.\n\n#ПрофилактикаТСПК","views":{"count":755}},{"inner_type":"wall_wallpost","donut":{"is_donut":false},"comments":{"can_post":1,"can_view":1,"count":0,"groups_can_post":true},"marked_as_ads":0,"hash":"jlxPliEOJS__DQsMUg","type":"post","push_subscription":{"is_subscribed":false},"attachments":[{"type":"video","video":{"response_type":"full","access_key":"baca2bcbf77167f40a","can_like":1,"can_repost":1,"can_subscribe":1,"can_add":1,"comments":0,"date":1743772805,"description":"","duration":46,"image":[{"url":"https:\/\/i.mycdn.me\/getVideoPreview?id=7806703897182&idx=0&type=39&tkn=eV3j2MDAyb7II9S9xMk1a0WteEs&fn=vid_s","width":130,"height":96,"with_padding":1},{"url":"https:\/\/i.mycdn.me\/getVideoPreview?id=7806703897182&idx=0&type=39&tkn=eV3j2MDAyb7II9S9xMk1a0WteEs&fn=vid_m","width":160,"height":120,"with_padding":1},{"url":"https:\/\/i.mycdn.me\/getVideoPreview?id=7806703897182&idx=0&type=39&tkn=eV3j2MDAyb7II9S9xMk1a0WteEs&fn=vid_l","width":320,"height":240,"with_padding":1},{"url":"https:\/\/i.mycdn.me\/getVideoPreview?id=7806703897182&idx=0&type=39&tkn=eV3j2MDAyb7II9S9xMk1a0WteEs&fn=vid_x","width":800,"height":450,"with_padding":1},{"url":"https:\/\/i.mycdn.me\/getVideoPreview?id=7806703897182&idx=0&type=39&tkn=eV3j2MDAyb7II9S9xMk1a0WteEs&fn=vid_w","width":405,"height":720},{"url":"https:\/\/i.mycdn.me\/getVideoPreview?id=7806703897182&idx=0&type=39&tkn=eV3j2MDAyb7II9S9xMk1a0WteEs&fn=vid_t","width":320,"height":569},{"url":"https:\/\/i.mycdn.me\/getVideoPreview?id=7806703897182&idx=0&type=39&tkn=eV3j2MDAyb7II9S9xMk1a0WteEs&fn=vid_u","width":720,"height":1280}],"first_frame":[{"url":"https:\/\/i.mycdn.me\/getVideoPreview?id=7806703897182&idx=0&type=39&tkn=eV3j2MDAyb7II9S9xMk1a0WteEs&fn=vid_f","width":227,"height":405},{"url":"https:\/\/i.mycdn.me\/getVideoPreview?id=7806703897182&idx=0&type=39&tkn=eV3j2MDAyb7II9S9xMk1a0WteEs&fn=vid_md","width":151,"height":270},{"url":"https:\/\/i.mycdn.me\/getVideoPreview?id=7806703897182&idx=0&type=39&tkn=eV3j2MDAyb7II9S9xMk1a0WteEs&fn=vid_d","width":75,"height":135},{"url":"https:\/\/i.mycdn.me\/getVideoPreview?id=7806703897182&idx=0&type=39&tkn=eV3j2MDAyb7II9S9xMk1a0WteEs&fn=vid_sm","width":40,"height":72},{"url":"https:\/\/i.mycdn.me\/getVideoPreview?id=7806703897182&idx=0&type=39&tkn=eV3j2MDAyb7II9S9xMk1a0WteEs&fn=vid_h","width":303,"height":540},{"url":"https:\/\/i.mycdn.me\/getVideoPreview?id=7806703897182&idx=0&type=39&tkn=eV3j2MDAyb7II9S9xMk1a0WteEs&fn=vid_w","width":405,"height":720}],"width":1080,"height":1920,"id":456240415,"owner_id":-174700694,"title":"Video by ТСПК_Онлайн","track_code":"video_70300ae6LXfB7ah8BkuBpznuGjdlFWiwMOswIOyJDcEUAne3vyIaVNzsqXEFJImnOOhFA1AjWoQA3woV6P5srXgCeJqOFS5jEyNgt86ETm7_2w","type":"video","views":961,"local_views":961,"can_dislike":1,"should_stretch":false}}],"date":1743772297,"edited":1743832841,"from_id":-174700694,"geo":{"coordinates":"53.515005882634 49.407335213457","place":{"discriminator":"place","created":1695755267,"id":203642860,"is_deleted":false,"latitude":53.514988,"longitude":49.407332,"title":"Tolyatti","total_checkins":37604,"updated":1695755267,"category":49,"category_object":{"id":49,"title":"City","icons":[{"url":"place.png","width":0,"height":0}]}},"type":"place"},"id":8682,"likes":{"can_like":1,"count":33,"user_likes":0,"can_publish":1,"repost_disabled":false},"reaction_set_id":"reactions","reactions":{"count":33,"items":[{"id":0,"count":33}]},"owner_id":-174700694,"post_source":{"type":"vk"},"post_type":"post","reposts":{"count":9,"user_reposted":0},"text":"Как понять какая профессия тебе по-настоящему подходит? Попробовать на практике! ✨\n\nВыбор профессии — это не просто слова, это жизнь, и важно понять, что тебе действительно близко! Нельзя решить, кем стать, не попробовав себя в реальной работе. Это как примерить на себя роль героя, прежде чем стать им по-настоящему! 🦸‍♂️\n\nМы в ТСПК понимаем, как важно дать школьникам возможность почувствовать себя в разных профессиях, и именно поэтому сегодня наши амбассадоры провели мастер-классы для [club186731144|МБУ «Школа № 34»] и [club191315539|МБУ «Школа имени С.П. Королёва»] ! \n\nВ ходе мастер-классов школьники погрузились в мир педагогики, ИТ, физической культуры и дошкольного воспитания, познакомились с профессиями изнутри и даже попробовали себя в реальных ситуациях! Это был не просто теоретический опыт, а шанс почувствовать, что значит работать в этой сфере. 💡\n\nЗачем гадать и сомневаться, когда можно взять и попробовать? Ведь только так можно понять, что именно твоё, и уверенно двигаться к своей цели! 🚀\n\np.s.: выражаем огромную благодарность нашим замечательным амбассадорам❤️ В очередной раз мы наблюдали прекрасную работу наших молодых профессионалов 🔥\n\n#ВЧД2025 \n#Профессионалы \n#СПО\n#Профессионалы63\n#85летСПО\n#ВсероссийскоеДвижениеПрофессионалы\n#ДействуйКакПрофессионал\n#ПрофессионалыСделаноВРоссии\n#Амбассадоры_Профессионалитета #Профессионалитет #Первый_Педагогический #ТСПК_в_сердце","views":{"count":1130}},{"inner_type":"wall_wallpost","donut":{"is_donut":false},"comments":{"can_post":1,"can_view":1,"count":0,"groups_can_post":true},"marked_as_ads":0,"hash":"RERxrMDA3fo2hIG-0Q","type":"post","push_subscription":{"is_subscribed":false},"attachments":[{"type":"video","video":{"response_type":"full","access_key":"4c2449d60d816dc37e","can_like":1,"can_repost":1,"can_subscribe":1,"can_add":1,"comments":0,"date":1743754486,"description":"","duration":115,"image":[{"url":"https:\/\/i.mycdn.me\/getVideoPreview?id=7890617764448&idx=2&type=39&tkn=ObZ47J5Ozcqe5FtUrcx-_tBY6qg&fn=vid_s","width":130,"height":96,"with_padding":1},{"url":"https:\/\/i.mycdn.me\/getVideoPreview?id=7890617764448&idx=2&type=39&tkn=ObZ47J5Ozcqe5FtUrcx-_tBY6qg&fn=vid_m","width":160,"height":120,"with_padding":1},{"url":"https:\/\/i.mycdn.me\/getVideoPreview?id=7890617764448&idx=2&type=39&tkn=ObZ47J5Ozcqe5FtUrcx-_tBY6qg&fn=vid_l","width":320,"height":240,"with_padding":1},{"url":"https:\/\/i.mycdn.me\/getVideoPreview?id=7890617764448&idx=2&type=39&tkn=ObZ47J5Ozcqe5FtUrcx-_tBY6qg&fn=vid_x","width":800,"height":450,"with_padding":1},{"url":"https:\/\/i.mycdn.me\/getVideoPreview?id=7890617764448&idx=2&type=39&tkn=ObZ47J5Ozcqe5FtUrcx-_tBY6qg&fn=vid_w","width":720,"height":720},{"url":"https:\/\/i.mycdn.me\/getVideoPreview?id=7890617764448&idx=2&type=39&tkn=ObZ47J5Ozcqe5FtUrcx-_tBY6qg&fn=vid_t","width":320,"height":320},{"url":"https:\/\/i.mycdn.me\/getVideoPreview?id=7890617764448&idx=2&type=39&tkn=ObZ47J5Ozcqe5FtUrcx-_tBY6qg&fn=vid_u","width":720,"height":720}],"first_frame":[{"url":"https:\/\/i.mycdn.me\/getVideoPreview?id=7890617764448&idx=0&type=39&tkn=cmQWDwfZfV-ei3hH6bjTFqo40l4&fn=vid_f","width":405,"height":405},{"url":"https:\/\/i.mycdn.me\/getVideoPreview?id=7890617764448&idx=0&type=39&tkn=cmQWDwfZfV-ei3hH6bjTFqo40l4&fn=vid_md","width":270,"height":270},{"url":"https:\/\/i.mycdn.me\/getVideoPreview?id=7890617764448&idx=0&type=39&tkn=cmQWDwfZfV-ei3hH6bjTFqo40l4&fn=vid_d","width":135,"height":135},{"url":"https:\/\/i.mycdn.me\/getVideoPreview?id=7890617764448&idx=0&type=39&tkn=cmQWDwfZfV-ei3hH6bjTFqo40l4&fn=vid_sm","width":72,"height":72},{"url":"https:\/\/i.mycdn.me\/getVideoPreview?id=7890617764448&idx=0&type=39&tkn=cmQWDwfZfV-ei3hH6bjTFqo40l4&fn=vid_h","width":540,"height":540},{"url":"https:\/\/i.mycdn.me\/getVideoPreview?id=7890617764448&idx=0&type=39&tkn=cmQWDwfZfV-ei3hH6bjTFqo40l4&fn=vid_w","width":720,"height":720}],"width":1080,"height":1080,"id":456271127,"owner_id":643853031,"title":"Антитеррор","track_code":"video_d7093bf8IChtslBRipzK1rOt5S7nplK4c2cEE8Q13BMzROGgPq0UC2uwWl3gl8zSu_LRG9GUZYlCXjMXs1SwfzNLzJEJmSPEpHmclkBQBRqD","type":"video","views":23616,"local_views":23616,"can_dislike":1,"should_stretch":false}}],"date":1743760474,"from_id":-174700694,"id":8679,"likes":{"can_like":1,"count":8,"user_likes":0,"can_publish":1,"repost_disabled":false},"reaction_set_id":"reactions","reactions":{"count":8,"items":[{"id":0,"count":8}]},"owner_id":-174700694,"post_source":{"type":"api"},"post_type":"post","reposts":{"count":0,"user_reposted":0},"text":"Терроризм - это насилие и жестокость. Цель террористов - паника в обществе. Главная мера противодействия террору — не бояться и не поддаваться на провокации.\n\nНе позволяйте втянуть себя в противоправную деятельность! Будьте внимательны и осторожны!\n\nРасскажите своим друзьям о простых правилах безопасности.\n\nТерроризму нет места в России!","views":{"count":512}}],"reaction_sets":[{"id":"reactions","items":[{"id":0,"title":"Like","asset":{"animation_url":"https:\/\/vk.com\/reaction\/3-reactions-0?c_uniq_tag=83b2081a8e4adfc36ee536f5f1b4ad470174c89678369a4b9dc5547614a3955e","images":[{"url":"https:\/\/vk.com\/reaction\/1-reactions-0-32?c_uniq_tag=464ba6bdc06e9f204a9b2c865a046355d835f601d8d82be4dc77e43a028741ff","width":32,"height":32},{"url":"https:\/\/vk.com\/reaction\/1-reactions-0-48?c_uniq_tag=e6bee176471af6e4f7ca0f57ac099847d57b8101bf07944e47b42b097a6d8455","width":48,"height":48},{"url":"https:\/\/vk.com\/reaction\/1-reactions-0-72?c_uniq_tag=d6f55fe94c0add8f817b447cbd804768752eb996c06ef222b39eb3fd35834780","width":72,"height":72},{"url":"https:\/\/vk.com\/reaction\/1-reactions-0-96?c_uniq_tag=0a64c3d34d3a1368b05716ff24f94ff51b2257a2287957423ced36a00b020cb6","width":96,"height":96},{"url":"https:\/\/vk.com\/reaction\/1-reactions-0-144?c_uniq_tag=47a911186fd9ce6d9aba1f9273e49ef70d1e0149e7470d1dae40941d81a1ece4","width":144,"height":144}],"title":{"color":{"foreground":{"light":"FF3347","dark":"FF5C5C"},"background":{"light":"FFEDED","dark":"3E2526"}}},"title_color":{"light":"FF3347","dark":"FF5C5C"}}},{"id":1,"title":"Haha","asset":{"animation_url":"https:\/\/vk.com\/reaction\/3-reactions-1?c_uniq_tag=a47193579880c0f53dd597a15d3bd57d4827820687c73d6128df2720647b42b9","images":[{"url":"https:\/\/vk.com\/reaction\/1-reactions-1-32?c_uniq_tag=2119d7ea78675f5702dcf43035f5f7fe13d6dd0f444b3a7d1735699d659b49b7","width":32,"height":32},{"url":"https:\/\/vk.com\/reaction\/1-reactions-1-48?c_uniq_tag=8f5eb3a1d6a6ec81aceff211782af3c9e9a5d1c837f0bfade6965a6844786f8b","width":48,"height":48},{"url":"https:\/\/vk.com\/reaction\/1-reactions-1-72?c_uniq_tag=c852fcad6e67059878dcf1905e3e416fd89fbc61222ead100935a6fcc1dab4c9","width":72,"height":72},{"url":"https:\/\/vk.com\/reaction\/1-reactions-1-96?c_uniq_tag=647ccf722698732a8b13033eadd1f02c5c917b0bdc3f9fb16d6cd0ade8706c99","width":96,"height":96},{"url":"https:\/\/vk.com\/reaction\/1-reactions-1-144?c_uniq_tag=68c571ccb2f08b9e0404e5307b41a48a057454b44375480a7a89f1dc8fb8b521","width":144,"height":144}],"title":{"color":{"foreground":{"light":"FF8000","dark":"FFC233"},"background":{"light":"FFF2D6","dark":"352E23"}}},"title_color":{"light":"FF8000","dark":"FFC233"}}},{"id":2,"title":"Wow!","asset":{"animation_url":"https:\/\/vk.com\/reaction\/3-reactions-2?c_uniq_tag=b946fcbe262642bc920331746b6eccd9f175bb17d8ef37e54d232fa35ca2c750","images":[{"url":"https:\/\/vk.com\/reaction\/1-reactions-2-32?c_uniq_tag=e919477a3e650ebae5d810b30dcc7529a52b072f2470327f95220b778abfb449","width":32,"height":32},{"url":"https:\/\/vk.com\/reaction\/1-reactions-2-48?c_uniq_tag=2a6544dce8827d216db7ea91eafc726cd3a823f5d465ba00216901a6de2801ad","width":48,"height":48},{"url":"https:\/\/vk.com\/reaction\/1-reactions-2-72?c_uniq_tag=5a0663f3d38dd6fbcf3e4973610d50641420631c9df30b6cf80eee0dd5c5efee","width":72,"height":72},{"url":"https:\/\/vk.com\/reaction\/1-reactions-2-96?c_uniq_tag=51275507a335aeafd7c43735d92d11a6b3acf2bb5595273a44a4f844c055b2ce","width":96,"height":96},{"url":"https:\/\/vk.com\/reaction\/1-reactions-2-144?c_uniq_tag=223a080cabb1e69212b9b1cdb455dcfb8bcbbdc40d93ae339717ecd32ea95f4c","width":144,"height":144}],"title":{"color":{"foreground":{"light":"FF8000","dark":"FFC233"},"background":{"light":"FFF2D6","dark":"352E23"}}},"title_color":{"light":"FF8000","dark":"FFC233"}}},{"id":3,"title":"Love","asset":{"animation_url":"https:\/\/vk.com\/reaction\/3-reactions-3?c_uniq_tag=c6ed3add99e841dccda5479c8e21779954e61e0fba15f94a2ae16706df492123","images":[{"url":"https:\/\/vk.com\/reaction\/1-reactions-3-32?c_uniq_tag=a95fe4eb836477892e54dcd8f464598e49a611249ec93d5eb7d7a1401cb77cff","width":32,"height":32},{"url":"https:\/\/vk.com\/reaction\/1-reactions-3-48?c_uniq_tag=eda1a2c18d733b356babdeed5f52cdcc64dd59f1f69776a133fc34a5627eecee","width":48,"height":48},{"url":"https:\/\/vk.com\/reaction\/1-reactions-3-72?c_uniq_tag=be09c5080773a9ba78984406588c7371e48073e80b842eb7c9a817f7b435379b","width":72,"height":72},{"url":"https:\/\/vk.com\/reaction\/1-reactions-3-96?c_uniq_tag=b08f5ff31b4bd18e465f14262708e4aac56d34f343b8d355171df7d73bb34497","width":96,"height":96},{"url":"https:\/\/vk.com\/reaction\/1-reactions-3-144?c_uniq_tag=484984c408a4b1f82d51229ce061ccbc5ad2efffbf2b684636ecfaa60f567f89","width":144,"height":144}],"title":{"color":{"foreground":{"light":"FF8000","dark":"FFC233"},"background":{"light":"FFF2D6","dark":"352E23"}}},"title_color":{"light":"FF8000","dark":"FFC233"}}},{"id":5,"title":"Sad","asset":{"animation_url":"https:\/\/vk.com\/reaction\/3-reactions-5?c_uniq_tag=c61122c8c334154cb10ccf0e0687057bf1f0f40c2817198b2e1150df534c22c4","images":[{"url":"https:\/\/vk.com\/reaction\/1-reactions-5-32?c_uniq_tag=a07ac888553814f1cbc8c9342b636bf30ca6d80d14e7e38170ea02dad0bfafbf","width":32,"height":32},{"url":"https:\/\/vk.com\/reaction\/1-reactions-5-48?c_uniq_tag=31bcb230babad96120a62589c52af22811aaba54d4ed73a36cfd499d9d94102f","width":48,"height":48},{"url":"https:\/\/vk.com\/reaction\/1-reactions-5-72?c_uniq_tag=a840d0eb581c133d97638ff5bf34f4b33f3fb8557b932cfe3516925b88e2f151","width":72,"height":72},{"url":"https:\/\/vk.com\/reaction\/1-reactions-5-96?c_uniq_tag=8cff3bac94202cbb5bee1d598f113134e0038804a3837be750f28ff27d3ffb05","width":96,"height":96},{"url":"https:\/\/vk.com\/reaction\/1-reactions-5-144?c_uniq_tag=8bf31a92656dd0c0d3482505bf1b6fb3d2493a3e4c93e0e62723aef81c7da052","width":144,"height":144}],"title":{"color":{"foreground":{"light":"4986CC","dark":"71AAEB"},"background":{"light":"EDF3FA","dark":"27303C"}}},"title_color":{"light":"4986CC","dark":"71AAEB"}}},{"id":4,"title":"&$#%!","asset":{"animation_url":"https:\/\/vk.com\/reaction\/3-reactions-4?c_uniq_tag=063e6b2dd888bb5a9716cf6153f03bf9c0c9707713b857eed8fe1e4e09aea2b3","images":[{"url":"https:\/\/vk.com\/reaction\/1-reactions-4-32?c_uniq_tag=ac5ab70367285c3fbbee7ba2adde88cbb65db2d35e05b09b4ae5593ee0bcc535","width":32,"height":32},{"url":"https:\/\/vk.com\/reaction\/1-reactions-4-48?c_uniq_tag=c80e3224c299a73384c057ff065c9458dcd533d57a1458875eb98883c3a96783","width":48,"height":48},{"url":"https:\/\/vk.com\/reaction\/1-reactions-4-72?c_uniq_tag=a0eddba1ec31f96adbb9afa2c6c14bec055b95f8d9f113bdf759fb5a9c9054f0","width":72,"height":72},{"url":"https:\/\/vk.com\/reaction\/1-reactions-4-96?c_uniq_tag=5495709e616048fd43683ac693ebd09f3615c797af2493d0334402befded2885","width":96,"height":96},{"url":"https:\/\/vk.com\/reaction\/1-reactions-4-144?c_uniq_tag=a79fce98e0d7769284290ab78936b3aa6d15a42caa50e6071bdeb5013d950251","width":144,"height":144}],"title":{"color":{"foreground":{"light":"EF5203","dark":"FA5300"},"background":{"light":"FDEBE8","dark":"3C2421"}}},"title_color":{"light":"EF5203","dark":"FA5300"}}}]}]}}